{"version": 0.6, "generator": "Overpass API 0.7.56.9 76e5016d", "osm3s": {"timestamp_osm_base": "2021-08-30T15:52:22Z", "copyright": "The data included in this document is from www.openstreetmap.org. The data is made available under ODbL."}, "elements": [{"type": "node", "id": 222469125, "lat": 30.6314812, "lon": -96.230229}, {"type": "node", "id": 222469502, "lat": 30.6315372, "lon": -96.2205964}, {"type": "node", "id": 222476183, "lat": 30.6138425, "lon": -96.1932503}, {"type": "node", "id": 222554292, "lat": 30.6179344, "lon": -96.1993063}, {"type": "node", "id": 222566673, "lat": 30.6218074, "lon": -96.2036217, "tags": {"highway": "traffic_signals", "traffic_signals": "signal"}}, {"type": "node", "id": 222638100, "lat": 30.6315891, "lon": -96.2222833}, {"type": "node", "id": 222638116, "lat": 30.6315774, "lon": -96.2214281}, {"type": "node", "id": 222638130, "lat": 30.6314871, "lon": -96.220012}, {"type": "node", "id": 222638135, "lat": 30.631439, "lon": -96.219477}, {"type": "node", "id": 222638139, "lat": 30.6304534, "lon": -96.2136678}, {"type": "node", "id": 222638144, "lat": 30.6303723, "lon": -96.2133588}, {"type": "node", "id": 222638146, "lat": 30.6302834, "lon": -96.2130421}, {"type": "node", "id": 222638147, "lat": 30.630183, "lon": -96.2127833}, {"type": "node", "id": 222638151, "lat": 30.6300671, "lon": -96.2125052}, {"type": "node", "id": 222638154, "lat": 30.6299242, "lon": -96.2121614}, {"type": "node", "id": 222638159, "lat": 30.6297928, "lon": -96.2118948}, {"type": "node", "id": 222638164, "lat": 30.6296268, "lon": -96.211636}, {"type": "node", "id": 222638168, "lat": 30.6294993, "lon": -96.2114468}, {"type": "node", "id": 222638174, "lat": 30.6293448, "lon": -96.2112343}, {"type": "node", "id": 222638181, "lat": 30.6290667, "lon": -96.2108751}, {"type": "node", "id": 222638185, "lat": 30.6280546, "lon": -96.2096738}, {"type": "node", "id": 222638210, "lat": 30.6266374, "lon": -96.2079872}, {"type": "node", "id": 222638213, "lat": 30.6261181, "lon": -96.20746}, {"type": "node", "id": 222638219, "lat": 30.6247018, "lon": -96.2062089}, {"type": "node", "id": 222638231, "lat": 30.6202855, "lon": -96.2022234}, {"type": "node", "id": 222638235, "lat": 30.6199572, "lon": -96.2019337}, {"type": "node", "id": 222638239, "lat": 30.6196675, "lon": -96.201644}, {"type": "node", "id": 222638245, "lat": 30.6193971, "lon": -96.2013697}, {"type": "node", "id": 222638250, "lat": 30.6191422, "lon": -96.201053}, {"type": "node", "id": 222638254, "lat": 30.6188872, "lon": -96.2007169}, {"type": "node", "id": 222638255, "lat": 30.6186632, "lon": -96.2004157}, {"type": "node", "id": 222638259, "lat": 30.6182653, "lon": -96.1997938}, {"type": "node", "id": 222638267, "lat": 30.6119845, "lon": -96.1905}, {"type": "node", "id": 222638269, "lat": 30.6115944, "lon": -96.1899013}, {"type": "node", "id": 222638273, "lat": 30.6111617, "lon": -96.1892833}, {"type": "node", "id": 222638279, "lat": 30.6108991, "lon": -96.1888583}, {"type": "node", "id": 222638283, "lat": 30.6107677, "lon": -96.1886034}, {"type": "node", "id": 222638286, "lat": 30.610621, "lon": -96.1883253}, {"type": "node", "id": 222638290, "lat": 30.6103776, "lon": -96.1878077}, {"type": "node", "id": 222638307, "lat": 30.6074068, "lon": -96.1813507}, {"type": "node", "id": 224696564, "lat": 30.6063049, "lon": -95.901067}, {"type": "node", "id": 224696575, "lat": 30.5981516, "lon": -96.0978095}, {"type": "node", "id": 224696644, "lat": 30.6028109, "lon": -95.907504}, {"type": "node", "id": 224696691, "lat": 30.6576702, "lon": -95.9640695}, {"type": "node", "id": 224697228, "lat": 30.7561037, "lon": -95.953061}, {"type": "node", "id": 224697904, "lat": 30.6140039, "lon": -95.886618}, {"type": "node", "id": 224698147, "lat": 30.4051345, "lon": -96.0536879}, {"type": "node", "id": 224698684, "lat": 30.7304916, "lon": -95.9601746}, {"type": "node", "id": 224703843, "lat": 30.4000339, "lon": -96.0627802}, {"type": "node", "id": 224704961, "lat": 30.6035314, "lon": -96.1724918}, {"type": "node", "id": 224706701, "lat": 30.5913805, "lon": -95.982875}, {"type": "node", "id": 224707368, "lat": 30.6038288, "lon": -96.1550592}, {"type": "node", "id": 224707832, "lat": 30.604233, "lon": -96.1496243}, {"type": "node", "id": 224708201, "lat": 30.4944506, "lon": -95.9887236}, {"type": "node", "id": 224708461, "lat": 30.5919161, "lon": -95.9888403}, {"type": "node", "id": 224708482, "lat": 30.5327003, "lon": -95.9803311}, {"type": "node", "id": 224708556, "lat": 30.5338043, "lon": -95.9795129}, {"type": "node", "id": 224708603, "lat": 30.6313319, "lon": -95.872654}, {"type": "node", "id": 224710043, "lat": 30.6989395, "lon": -95.9688773}, {"type": "node", "id": 224710249, "lat": 30.819193, "lon": -95.9476381}, {"type": "node", "id": 224712136, "lat": 30.576559, "lon": -95.948949}, {"type": "node", "id": 224712143, "lat": 30.572563, "lon": -95.951795}, {"type": "node", "id": 224712159, "lat": 30.5305194, "lon": -95.9818917}, {"type": "node", "id": 224712171, "lat": 30.5072021, "lon": -95.9906528}, {"type": "node", "id": 224712269, "lat": 30.3991512, "lon": -96.0652191}, {"type": "node", "id": 224714304, "lat": 30.7315284, "lon": -95.9598814}, {"type": "node", "id": 224715646, "lat": 30.5946275, "lon": -96.0768174}, {"type": "node", "id": 224715949, "lat": 30.5855113, "lon": -95.9470529}, {"type": "node", "id": 224715993, "lat": 30.6018811, "lon": -96.1218511}, {"type": "node", "id": 224716227, "lat": 30.4032849, "lon": -96.0562819}, {"type": "node", "id": 224716269, "lat": 30.6454569, "lon": -95.8534959}, {"type": "node", "id": 224716608, "lat": 30.593935, "lon": -96.012018}, {"type": "node", "id": 224717336, "lat": 30.823433, "lon": -95.9473947}, {"type": "node", "id": 224718453, "lat": 30.5334954, "lon": -95.9797457}, {"type": "node", "id": 224718627, "lat": 30.643331, "lon": -95.8548969}, {"type": "node", "id": 224720037, "lat": 30.5956088, "lon": -96.034768}, {"type": "node", "id": 224721008, "lat": 30.6776002, "lon": -95.9710199}, {"type": "node", "id": 224721168, "lat": 30.594114, "lon": -96.013883}, {"type": "node", "id": 224721245, "lat": 30.5942909, "lon": -96.016173}, {"type": "node", "id": 224721635, "lat": 30.59512, "lon": -95.921439}, {"type": "node", "id": 224721867, "lat": 30.597354, "lon": -95.919162}, {"type": "node", "id": 224723902, "lat": 30.6155736, "lon": -95.8860836}, {"type": "node", "id": 224724760, "lat": 30.6228479, "lon": -95.8836231}, {"type": "node", "id": 224724929, "lat": 30.5946381, "lon": -96.081748}, {"type": "node", "id": 224724975, "lat": 30.4049596, "lon": -96.0539447}, {"type": "node", "id": 224725662, "lat": 30.593498, "lon": -96.007095}, {"type": "node", "id": 224725996, "lat": 30.5970222, "lon": -95.9194918}, {"type": "node", "id": 224726111, "lat": 30.5908125, "lon": -95.9763278}, {"type": "node", "id": 224726377, "lat": 30.660724, "lon": -95.9640447}, {"type": "node", "id": 224727666, "lat": 30.4012339, "lon": -96.059669}, {"type": "node", "id": 224727719, "lat": 30.4017083, "lon": -96.0588252}, {"type": "node", "id": 224727760, "lat": 30.4034675, "lon": -96.0560163}, {"type": "node", "id": 224728796, "lat": 30.6729901, "lon": -95.9686779}, {"type": "node", "id": 224731522, "lat": 30.56165, "lon": -95.959633}, {"type": "node", "id": 224731583, "lat": 30.5492862, "lon": -95.9684693}, {"type": "node", "id": 224731620, "lat": 30.552773, "lon": -95.965959}, {"type": "node", "id": 224731645, "lat": 30.552613, "lon": -95.966091}, {"type": "node", "id": 224731971, "lat": 30.6017858, "lon": -96.1178401}, {"type": "node", "id": 224732353, "lat": 30.608138, "lon": -95.898139}, {"type": "node", "id": 224733367, "lat": 30.5041216, "lon": -95.9911517}, {"type": "node", "id": 224733538, "lat": 30.8203784, "lon": -95.9475779}, {"type": "node", "id": 224733738, "lat": 30.5951554, "lon": -96.0511534}, {"type": "node", "id": 224733876, "lat": 30.6050507, "lon": -96.1368347}, {"type": "node", "id": 224734270, "lat": 30.605626, "lon": -96.1775258}, {"type": "node", "id": 224734493, "lat": 30.5411041, "lon": -95.9742883}, {"type": "node", "id": 224734811, "lat": 30.6017236, "lon": -96.1206702}, {"type": "node", "id": 224735825, "lat": 30.5087656, "lon": -95.9903922}, {"type": "node", "id": 224735857, "lat": 30.6134888, "lon": -95.8875285}, {"type": "node", "id": 224736045, "lat": 30.429223, "lon": -96.0414724}, {"type": "node", "id": 224736487, "lat": 30.513658, "lon": -95.989564}, {"type": "node", "id": 224736513, "lat": 30.5216693, "lon": -95.9880333}, {"type": "node", "id": 224736547, "lat": 30.525032, "lon": -95.985787}, {"type": "node", "id": 224736617, "lat": 30.5291876, "lon": -95.982822}, {"type": "node", "id": 224736669, "lat": 30.531386, "lon": -95.981205}, {"type": "node", "id": 224737702, "lat": 30.424729, "lon": -96.0445312}, {"type": "node", "id": 224738358, "lat": 30.4150606, "lon": -96.0482699}, {"type": "node", "id": 224738461, "lat": 30.4001812, "lon": -96.0623717}, {"type": "node", "id": 224738594, "lat": 30.4013454, "lon": -96.0594721}, {"type": "node", "id": 224739204, "lat": 30.624605, "lon": -95.8830102}, {"type": "node", "id": 224739516, "lat": 30.513969, "lon": -95.989514}, {"type": "node", "id": 224740304, "lat": 30.625405, "lon": -95.9535119}, {"type": "node", "id": 224741051, "lat": 30.41356, "lon": -96.048838}, {"type": "node", "id": 224742068, "lat": 30.5939979, "lon": -95.92264}, {"type": "node", "id": 224742195, "lat": 30.5889808, "lon": -95.928027}, {"type": "node", "id": 224742381, "lat": 30.5836989, "lon": -95.9414011}, {"type": "node", "id": 224743362, "lat": 30.4395626, "lon": -96.0322747}, {"type": "node", "id": 224743596, "lat": 30.604257, "lon": -95.949827}, {"type": "node", "id": 224743634, "lat": 30.5981524, "lon": -95.9479975}, {"type": "node", "id": 224743678, "lat": 30.5868892, "lon": -95.951606}, {"type": "node", "id": 224743764, "lat": 30.4118502, "lon": -96.0494972}, {"type": "node", "id": 224743800, "lat": 30.589996, "lon": -95.967159}, {"type": "node", "id": 224744331, "lat": 30.468178, "lon": -96.012363}, {"type": "node", "id": 224744348, "lat": 30.4663503, "lon": -96.01448}, {"type": "node", "id": 224744425, "lat": 30.4635118, "lon": -96.0177642}, {"type": "node", "id": 224744545, "lat": 30.590528, "lon": -95.9255741}, {"type": "node", "id": 224745093, "lat": 30.626972, "lon": -95.8820842}, {"type": "node", "id": 224745215, "lat": 30.626467, "lon": -95.8823432}, {"type": "node", "id": 224745910, "lat": 30.5949912, "lon": -96.0567795}, {"type": "node", "id": 224745978, "lat": 30.5951741, "lon": -96.0502279}, {"type": "node", "id": 224745996, "lat": 30.594741, "lon": -96.021122}, {"type": "node", "id": 224746604, "lat": 30.4356522, "lon": -96.0357573}, {"type": "node", "id": 224746723, "lat": 30.4004533, "lon": -96.0616647}, {"type": "node", "id": 224746934, "lat": 30.4338742, "lon": -96.0373612}, {"type": "node", "id": 224747886, "lat": 30.5002484, "lon": -95.9913462}, {"type": "node", "id": 224748090, "lat": 30.566604, "lon": -95.956074}, {"type": "node", "id": 224748802, "lat": 30.5895381, "lon": -95.926695}, {"type": "node", "id": 224748984, "lat": 30.69457, "lon": -95.970069}, {"type": "node", "id": 224749012, "lat": 30.6090655, "lon": -95.9506524}, {"type": "node", "id": 224749043, "lat": 30.687411, "lon": -95.9720575}, {"type": "node", "id": 224749309, "lat": 30.614958, "lon": -95.8862441}, {"type": "node", "id": 224751075, "lat": 30.7786244, "lon": -95.949915}, {"type": "node", "id": 224751468, "lat": 30.419651, "lon": -96.046485}, {"type": "node", "id": 224751534, "lat": 30.5917703, "lon": -95.9453307}, {"type": "node", "id": 224751780, "lat": 30.7365197, "lon": -95.9585268}, {"type": "node", "id": 224751883, "lat": 30.670063, "lon": -95.9672007}, {"type": "node", "id": 224752067, "lat": 30.5522, "lon": -95.9663864}, {"type": "node", "id": 224752446, "lat": 30.662816, "lon": -95.9643023}, {"type": "node", "id": 224754455, "lat": 30.6869048, "lon": -95.9721945}, {"type": "node", "id": 224755331, "lat": 30.662038, "lon": -95.9641855}, {"type": "node", "id": 224755653, "lat": 30.8061967, "lon": -95.9483698}, {"type": "node", "id": 224756345, "lat": 30.577631, "lon": -95.948194}, {"type": "node", "id": 224756379, "lat": 30.5808589, "lon": -95.9458784}, {"type": "node", "id": 224756741, "lat": 30.4899921, "lon": -95.9881162}, {"type": "node", "id": 224756796, "lat": 30.487208, "lon": -95.9879073}, {"type": "node", "id": 224758235, "lat": 30.6114751, "lon": -95.8923157}, {"type": "node", "id": 224758278, "lat": 30.6106864, "lon": -95.8939265}, {"type": "node", "id": 224758284, "lat": 30.6103809, "lon": -95.8944997}, {"type": "node", "id": 224758491, "lat": 30.4959647, "lon": -95.9894331}, {"type": "node", "id": 224758506, "lat": 30.4999341, "lon": -95.9912295}, {"type": "node", "id": 224758706, "lat": 30.6118368, "lon": -95.891475}, {"type": "node", "id": 224759536, "lat": 30.4868643, "lon": -95.988212}, {"type": "node", "id": 224760094, "lat": 30.6122508, "lon": -95.8904661}, {"type": "node", "id": 224760922, "lat": 30.7535909, "lon": -95.9537879}, {"type": "node", "id": 224760945, "lat": 30.6511902, "lon": -95.9583108}, {"type": "node", "id": 224761010, "lat": 30.7470917, "lon": -95.9555849}, {"type": "node", "id": 224761354, "lat": 30.5848456, "lon": -95.9348131}, {"type": "node", "id": 224761947, "lat": 30.6970154, "lon": -95.9694057}, {"type": "node", "id": 224762166, "lat": 30.595668, "lon": -95.92088}, {"type": "node", "id": 224762416, "lat": 30.6521583, "lon": -95.9587453}, {"type": "node", "id": 224762765, "lat": 30.5946272, "lon": -96.0761846}, {"type": "node", "id": 224764280, "lat": 30.3989754, "lon": -96.0656911}, {"type": "node", "id": 224766069, "lat": 30.594637, "lon": -96.080721}, {"type": "node", "id": 224766147, "lat": 30.7776418, "lon": -95.9499314}, {"type": "node", "id": 224766201, "lat": 30.7745458, "lon": -95.9500194}, {"type": "node", "id": 224766580, "lat": 30.6018161, "lon": -96.1173054}, {"type": "node", "id": 224767227, "lat": 30.6478865, "lon": -95.9574098}, {"type": "node", "id": 224767697, "lat": 30.6547073, "lon": -95.9599381}, {"type": "node", "id": 224767888, "lat": 30.407761, "lon": -96.051522}, {"type": "node", "id": 224768367, "lat": 30.535815, "lon": -95.9781196}, {"type": "node", "id": 224768707, "lat": 30.4879869, "lon": -95.9876014}, {"type": "node", "id": 224768708, "lat": 30.4885214, "lon": -95.98767}, {"type": "node", "id": 224770068, "lat": 30.574827, "lon": -95.9502069}, {"type": "node", "id": 224770976, "lat": 30.8151693, "lon": -95.9478741}, {"type": "node", "id": 224771103, "lat": 30.594893, "lon": -96.0894583}, {"type": "node", "id": 224771797, "lat": 30.5817709, "lon": -95.9452928}, {"type": "node", "id": 224772640, "lat": 30.5946678, "lon": -96.0726989}, {"type": "node", "id": 224772654, "lat": 30.6017092, "lon": -96.1203045}, {"type": "node", "id": 224773166, "lat": 30.7057417, "lon": -95.9669897}, {"type": "node", "id": 224773385, "lat": 30.5917592, "lon": -95.986891}, {"type": "node", "id": 224773406, "lat": 30.593457, "lon": -96.006573}, {"type": "node", "id": 224773562, "lat": 30.776634, "lon": -95.9499572}, {"type": "node", "id": 224773698, "lat": 30.4849851, "lon": -95.9917444}, {"type": "node", "id": 224773886, "lat": 30.5835878, "lon": -95.9444954}, {"type": "node", "id": 224773896, "lat": 30.5848116, "lon": -95.9449862}, {"type": "node", "id": 224774232, "lat": 30.5946192, "lon": -96.0777954}, {"type": "node", "id": 224774539, "lat": 30.5114627, "lon": -95.9899174}, {"type": "node", "id": 224774576, "lat": 30.4769766, "lon": -96.0022987}, {"type": "node", "id": 224774881, "lat": 30.8389126, "lon": -95.9465419}, {"type": "node", "id": 224775143, "lat": 30.594649, "lon": -96.019984}, {"type": "node", "id": 224776171, "lat": 30.4590473, "lon": -96.022831}, {"type": "node", "id": 224776455, "lat": 30.6502724, "lon": -95.9579058}, {"type": "node", "id": 224777121, "lat": 30.637784, "lon": -95.8605369}, {"type": "node", "id": 224777855, "lat": 30.5946277, "lon": -96.0773071}, {"type": "node", "id": 224779112, "lat": 30.4819867, "lon": -95.9965717}, {"type": "node", "id": 224779761, "lat": 30.4895162, "lon": -95.9879989}, {"type": "node", "id": 224779766, "lat": 30.4908767, "lon": -95.988219}, {"type": "node", "id": 224780372, "lat": 30.4264093, "lon": -96.0437305}, {"type": "node", "id": 224780884, "lat": 30.4452019, "lon": -96.0275479}, {"type": "node", "id": 224781238, "lat": 30.7755933, "lon": -95.9500006}, {"type": "node", "id": 224781242, "lat": 30.7735756, "lon": -95.9500433}, {"type": "node", "id": 224782382, "lat": 30.6126847, "lon": -95.889437}, {"type": "node", "id": 224782921, "lat": 30.6131598, "lon": -95.8882543}, {"type": "node", "id": 224783380, "lat": 30.6559368, "lon": -95.8384448}, {"type": "node", "id": 224784051, "lat": 30.5287009, "lon": -95.9831951}, {"type": "node", "id": 224785957, "lat": 30.8486908, "lon": -95.9457245}, {"type": "node", "id": 224785988, "lat": 30.4094781, "lon": -96.0505492}, {"type": "node", "id": 224786132, "lat": 30.4461898, "lon": -96.0271868}, {"type": "node", "id": 224786149, "lat": 30.453716, "lon": -96.026314}, {"type": "node", "id": 224786255, "lat": 30.7572618, "lon": -95.9527582}, {"type": "node", "id": 224786984, "lat": 30.4863919, "lon": -95.9893523}, {"type": "node", "id": 224787801, "lat": 30.4056632, "lon": -96.0530827}, {"type": "node", "id": 224788097, "lat": 30.4938316, "lon": -95.9884846}, {"type": "node", "id": 224788847, "lat": 30.4842854, "lon": -95.9932308}, {"type": "node", "id": 224789284, "lat": 30.6035871, "lon": -96.1726732}, {"type": "node", "id": 224789289, "lat": 30.6034573, "lon": -96.1709136}, {"type": "node", "id": 224789291, "lat": 30.6035509, "lon": -96.1621898}, {"type": "node", "id": 224789293, "lat": 30.6035343, "lon": -96.1593531}, {"type": "node", "id": 224789302, "lat": 30.6047475, "lon": -96.1425007}, {"type": "node", "id": 224789311, "lat": 30.6050475, "lon": -96.1385353}, {"type": "node", "id": 224789313, "lat": 30.60404, "lon": -96.131964}, {"type": "node", "id": 224789317, "lat": 30.602625, "lon": -96.125234}, {"type": "node", "id": 224789319, "lat": 30.6020043, "lon": -96.1224581}, {"type": "node", "id": 224789323, "lat": 30.6021884, "lon": -96.1086523}, {"type": "node", "id": 224789325, "lat": 30.602073, "lon": -96.1078696}, {"type": "node", "id": 224789329, "lat": 30.6014266, "lon": -96.1056514}, {"type": "node", "id": 224789335, "lat": 30.5994633, "lon": -96.100995}, {"type": "node", "id": 224789340, "lat": 30.5953008, "lon": -96.0908444}, {"type": "node", "id": 224789344, "lat": 30.5949539, "lon": -96.0897108}, {"type": "node", "id": 224789348, "lat": 30.5946343, "lon": -96.086227}, {"type": "node", "id": 224789361, "lat": 30.594737, "lon": -96.065196}, {"type": "node", "id": 224789365, "lat": 30.5949032, "lon": -96.059526}, {"type": "node", "id": 224789367, "lat": 30.595525, "lon": -96.039491}, {"type": "node", "id": 224789373, "lat": 30.595614, "lon": -96.031312}, {"type": "node", "id": 224789376, "lat": 30.5952999, "lon": -96.0279881}, {"type": "node", "id": 224789381, "lat": 30.593238, "lon": -96.003724}, {"type": "node", "id": 224789386, "lat": 30.5922561, "lon": -95.9925978}, {"type": "node", "id": 224789392, "lat": 30.591216, "lon": -95.981314}, {"type": "node", "id": 224789398, "lat": 30.589571, "lon": -95.962081}, {"type": "node", "id": 224789402, "lat": 30.5893421, "lon": -95.9601739}, {"type": "node", "id": 224789405, "lat": 30.5888292, "lon": -95.95789}, {"type": "node", "id": 224789408, "lat": 30.5882092, "lon": -95.955882}, {"type": "node", "id": 224789414, "lat": 30.584514, "lon": -95.944109}, {"type": "node", "id": 224789420, "lat": 30.5840691, "lon": -95.9425709}, {"type": "node", "id": 224789424, "lat": 30.583599, "lon": -95.9409884}, {"type": "node", "id": 224789428, "lat": 30.583529, "lon": -95.940113}, {"type": "node", "id": 224789430, "lat": 30.583827, "lon": -95.937599}, {"type": "node", "id": 224789434, "lat": 30.5840891, "lon": -95.9362726}, {"type": "node", "id": 224789438, "lat": 30.585678, "lon": -95.933953}, {"type": "node", "id": 224789440, "lat": 30.586663, "lon": -95.9330241}, {"type": "node", "id": 224789446, "lat": 30.5873021, "lon": -95.9323499}, {"type": "node", "id": 224789449, "lat": 30.5878509, "lon": -95.931363}, {"type": "node", "id": 224789453, "lat": 30.5892285, "lon": -95.9273098}, {"type": "node", "id": 224789457, "lat": 30.5900883, "lon": -95.9259798}, {"type": "node", "id": 224789462, "lat": 30.5910482, "lon": -95.9251847}, {"type": "node", "id": 224789465, "lat": 30.5923862, "lon": -95.9241935}, {"type": "node", "id": 224789469, "lat": 30.592642, "lon": -95.923967}, {"type": "node", "id": 224789473, "lat": 30.599031, "lon": -95.9174151}, {"type": "node", "id": 224789477, "lat": 30.5995384, "lon": -95.9167828}, {"type": "node", "id": 224789487, "lat": 30.5999898, "lon": -95.9158641}, {"type": "node", "id": 224789496, "lat": 30.602606, "lon": -95.908116}, {"type": "node", "id": 224789498, "lat": 30.6034411, "lon": -95.9057779}, {"type": "node", "id": 224789512, "lat": 30.60511, "lon": -95.902954}, {"type": "node", "id": 224789521, "lat": 30.6097968, "lon": -95.8955463}, {"type": "node", "id": 224789529, "lat": 30.610453, "lon": -95.894343}, {"type": "node", "id": 224789551, "lat": 30.6147691, "lon": -95.8863129}, {"type": "node", "id": 224789558, "lat": 30.619563, "lon": -95.88482}, {"type": "node", "id": 224789574, "lat": 30.6273284, "lon": -95.8818479}, {"type": "node", "id": 224789577, "lat": 30.6279402, "lon": -95.8812758}, {"type": "node", "id": 224789582, "lat": 30.628528, "lon": -95.8804257}, {"type": "node", "id": 224789587, "lat": 30.6289449, "lon": -95.8794719}, {"type": "node", "id": 224789595, "lat": 30.6304199, "lon": -95.875256}, {"type": "node", "id": 224789600, "lat": 30.631954, "lon": -95.87086}, {"type": "node", "id": 224789605, "lat": 30.6322413, "lon": -95.8701339}, {"type": "node", "id": 224789609, "lat": 30.632861, "lon": -95.8687725}, {"type": "node", "id": 224789614, "lat": 30.637139, "lon": -95.8614489}, {"type": "node", "id": 224789619, "lat": 30.6386678, "lon": -95.859381}, {"type": "node", "id": 224789623, "lat": 30.6420209, "lon": -95.8561378}, {"type": "node", "id": 224789625, "lat": 30.6439554, "lon": -95.8543935}, {"type": "node", "id": 224789629, "lat": 30.6486182, "lon": -95.8517398}, {"type": "node", "id": 224789633, "lat": 30.6496787, "lon": -95.850771}, {"type": "node", "id": 224789635, "lat": 30.6504667, "lon": -95.8494701}, {"type": "node", "id": 224789640, "lat": 30.65191, "lon": -95.8467695}, {"type": "node", "id": 224789643, "lat": 30.6538777, "lon": -95.8427309}, {"type": "node", "id": 224789651, "lat": 30.6572888, "lon": -95.8356279}, {"type": "node", "id": 224789655, "lat": 30.6579817, "lon": -95.8342349}, {"type": "node", "id": 224792067, "lat": 30.6101998, "lon": -95.9508544}, {"type": "node", "id": 224794498, "lat": 30.5433101, "lon": -95.9727605}, {"type": "node", "id": 224794756, "lat": 30.6803889, "lon": -95.9724666}, {"type": "node", "id": 224795466, "lat": 30.5597297, "lon": -95.9609923}, {"type": "node", "id": 224795560, "lat": 30.6005233, "lon": -95.948988}, {"type": "node", "id": 224799034, "lat": 30.613118, "lon": -95.9513685}, {"type": "node", "id": 224799797, "lat": 30.8419986, "lon": -95.9463729}, {"type": "node", "id": 224800644, "lat": 30.8382528, "lon": -95.9465727}, {"type": "node", "id": 224800847, "lat": 30.7798749, "lon": -95.9498678}, {"type": "node", "id": 224801236, "lat": 30.7914098, "lon": -95.9492128}, {"type": "node", "id": 224801375, "lat": 30.7911531, "lon": -95.9492362}, {"type": "node", "id": 224802136, "lat": 30.78903, "lon": -95.9493565}, {"type": "node", "id": 224802140, "lat": 30.801245, "lon": -95.9486663}, {"type": "node", "id": 224802167, "lat": 30.828828, "lon": -95.9470949}, {"type": "node", "id": 224802172, "lat": 30.8336639, "lon": -95.9468369}, {"type": "node", "id": 224802174, "lat": 30.8459126, "lon": -95.9461603}, {"type": "node", "id": 224802176, "lat": 30.8466117, "lon": -95.9460906}, {"type": "node", "id": 224802180, "lat": 30.852302, "lon": -95.945088}, {"type": "node", "id": 224802196, "lat": 30.4949335, "lon": -95.9889461}, {"type": "node", "id": 224802231, "lat": 30.509602, "lon": -95.990248}, {"type": "node", "id": 224802240, "lat": 30.512373, "lon": -95.989774}, {"type": "node", "id": 224802244, "lat": 30.514541, "lon": -95.989422}, {"type": "node", "id": 224802246, "lat": 30.5193808, "lon": -95.98866}, {"type": "node", "id": 224802250, "lat": 30.521476, "lon": -95.9881054}, {"type": "node", "id": 224802252, "lat": 30.5226929, "lon": -95.9874563}, {"type": "node", "id": 224802257, "lat": 30.5232876, "lon": -95.9870269}, {"type": "node", "id": 224802277, "lat": 30.571978, "lon": -95.952215}, {"type": "node", "id": 224802286, "lat": 30.5814596, "lon": -95.9454867}, {"type": "node", "id": 224802290, "lat": 30.5824498, "lon": -95.9449556}, {"type": "node", "id": 224802293, "lat": 30.5853752, "lon": -95.9437981}, {"type": "node", "id": 224802296, "lat": 30.586391, "lon": -95.943607}, {"type": "node", "id": 224802299, "lat": 30.587284, "lon": -95.94366}, {"type": "node", "id": 224802307, "lat": 30.589046, "lon": -95.944189}, {"type": "node", "id": 224802332, "lat": 30.594427, "lon": -95.94644}, {"type": "node", "id": 224802352, "lat": 30.6012008, "lon": -95.9492326}, {"type": "node", "id": 224802365, "lat": 30.6085005, "lon": -95.9505683}, {"type": "node", "id": 224802375, "lat": 30.6147463, "lon": -95.9516636}, {"type": "node", "id": 224802389, "lat": 30.621536, "lon": -95.9528476}, {"type": "node", "id": 224802398, "lat": 30.6303918, "lon": -95.9543852}, {"type": "node", "id": 224802401, "lat": 30.635937, "lon": -95.9553333}, {"type": "node", "id": 224802413, "lat": 30.6404728, "lon": -95.9561337}, {"type": "node", "id": 224802421, "lat": 30.6543848, "lon": -95.9597678}, {"type": "node", "id": 224802422, "lat": 30.6545625, "lon": -95.9598476}, {"type": "node", "id": 224802423, "lat": 30.6554319, "lon": -95.9605598}, {"type": "node", "id": 224802427, "lat": 30.6563921, "lon": -95.9620785}, {"type": "node", "id": 224802430, "lat": 30.6570685, "lon": -95.9634303}, {"type": "node", "id": 224802432, "lat": 30.657288, "lon": -95.9637325}, {"type": "node", "id": 224802436, "lat": 30.6575262, "lon": -95.9639623}, {"type": "node", "id": 224802440, "lat": 30.6580573, "lon": -95.9642737}, {"type": "node", "id": 224802444, "lat": 30.6590954, "lon": -95.964399}, {"type": "node", "id": 224802448, "lat": 30.6597645, "lon": -95.9642409}, {"type": "node", "id": 224802452, "lat": 30.6600787, "lon": -95.964134}, {"type": "node", "id": 224802456, "lat": 30.6612903, "lon": -95.9640813}, {"type": "node", "id": 224802463, "lat": 30.664305, "lon": -95.9645573}, {"type": "node", "id": 224802466, "lat": 30.6663896, "lon": -95.9653374}, {"type": "node", "id": 224802498, "lat": 30.6810069, "lon": -95.9727055}, {"type": "node", "id": 224802501, "lat": 30.6816706, "lon": -95.9728894}, {"type": "node", "id": 224802505, "lat": 30.6829387, "lon": -95.9730402}, {"type": "node", "id": 224802508, "lat": 30.6843299, "lon": -95.9728801}, {"type": "node", "id": 224802512, "lat": 30.6851892, "lon": -95.9726538}, {"type": "node", "id": 224802515, "lat": 30.694006, "lon": -95.970228}, {"type": "node", "id": 224802519, "lat": 30.7026518, "lon": -95.9678462}, {"type": "node", "id": 224802523, "lat": 30.7092672, "lon": -95.9660284}, {"type": "node", "id": 224802526, "lat": 30.7285042, "lon": -95.9607291}, {"type": "node", "id": 224802530, "lat": 30.7353127, "lon": -95.9588588}, {"type": "node", "id": 224802543, "lat": 30.7456712, "lon": -95.9559836}, {"type": "node", "id": 224802546, "lat": 30.750193, "lon": -95.954725}, {"type": "node", "id": 224802550, "lat": 30.750673, "lon": -95.954589}, {"type": "node", "id": 224802554, "lat": 30.7644556, "lon": -95.950773}, {"type": "node", "id": 224802558, "lat": 30.7669823, "lon": -95.9502409}, {"type": "node", "id": 224802580, "lat": 30.4916672, "lon": -95.9882914}, {"type": "node", "id": 224802586, "lat": 30.4931741, "lon": -95.9884067}, {"type": "node", "id": 224802598, "lat": 30.3993733, "lon": -96.0645539}, {"type": "node", "id": 224802605, "lat": 30.4015389, "lon": -96.0591161}, {"type": "node", "id": 224802608, "lat": 30.4020692, "lon": -96.0582183}, {"type": "node", "id": 224802611, "lat": 30.4038884, "lon": -96.0554216}, {"type": "node", "id": 224802614, "lat": 30.4054103, "lon": -96.0533665}, {"type": "node", "id": 224802616, "lat": 30.4059813, "lon": -96.0528066}, {"type": "node", "id": 224802619, "lat": 30.4071161, "lon": -96.0519478}, {"type": "node", "id": 224802625, "lat": 30.4101864, "lon": -96.050209}, {"type": "node", "id": 224802628, "lat": 30.4114028, "lon": -96.0496769}, {"type": "node", "id": 224802631, "lat": 30.412586, "lon": -96.0492172}, {"type": "node", "id": 224802639, "lat": 30.418214, "lon": -96.0470513}, {"type": "node", "id": 224802656, "lat": 30.425938, "lon": -96.0440072}, {"type": "node", "id": 224802660, "lat": 30.4276612, "lon": -96.0428383}, {"type": "node", "id": 224802664, "lat": 30.4284619, "lon": -96.0421516}, {"type": "node", "id": 224802668, "lat": 30.4322714, "lon": -96.0387731}, {"type": "node", "id": 224802688, "lat": 30.443576, "lon": -96.0287205}, {"type": "node", "id": 224802691, "lat": 30.4448073, "lon": -96.0277643}, {"type": "node", "id": 224802694, "lat": 30.4455919, "lon": -96.027371}, {"type": "node", "id": 224802698, "lat": 30.4459969, "lon": -96.0272488}, {"type": "node", "id": 224802701, "lat": 30.446807, "lon": -96.0270425}, {"type": "node", "id": 224802704, "lat": 30.4484019, "lon": -96.0269974}, {"type": "node", "id": 224802707, "lat": 30.4505706, "lon": -96.0271608}, {"type": "node", "id": 224802713, "lat": 30.4521509, "lon": -96.0269339}, {"type": "node", "id": 224802724, "lat": 30.4567307, "lon": -96.0247715}, {"type": "node", "id": 224802728, "lat": 30.4578072, "lon": -96.0240551}, {"type": "node", "id": 224802756, "lat": 30.483367, "lon": -95.9949604}, {"type": "node", "id": 224802757, "lat": 30.4835408, "lon": -95.9947238}, {"type": "node", "id": 224802758, "lat": 30.4840417, "lon": -95.993836}, {"type": "node", "id": 224802759, "lat": 30.4848184, "lon": -95.9920211}, {"type": "node", "id": 224802760, "lat": 30.4853364, "lon": -95.9913232}, {"type": "node", "id": 224802761, "lat": 30.4860197, "lon": -95.990338}, {"type": "node", "id": 224802762, "lat": 30.4876215, "lon": -95.9876764}, {"type": "node", "id": 229027768, "lat": 30.666142, "lon": -95.8079801}, {"type": "node", "id": 229028889, "lat": 30.6901185, "lon": -95.6740868}, {"type": "node", "id": 229032566, "lat": 30.6828288, "lon": -95.7541916}, {"type": "node", "id": 229032617, "lat": 30.6706775, "lon": -95.7932968}, {"type": "node", "id": 229032643, "lat": 30.6590543, "lon": -95.8308774}, {"type": "node", "id": 229032656, "lat": 30.6843254, "lon": -95.73512}, {"type": "node", "id": 229035541, "lat": 30.6783693, "lon": -95.7685145}, {"type": "node", "id": 229036830, "lat": 30.6648799, "lon": -95.8120739}, {"type": "node", "id": 229036900, "lat": 30.6670572, "lon": -95.8050178}, {"type": "node", "id": 229038410, "lat": 30.6757677, "lon": -95.7768121}, {"type": "node", "id": 229045382, "lat": 30.6792019, "lon": -95.7658424}, {"type": "node", "id": 229056381, "lat": 30.6843107, "lon": -95.7404574}, {"type": "node", "id": 229056518, "lat": 30.6843699, "lon": -95.7251121}, {"type": "node", "id": 229068269, "lat": 30.6976021, "lon": -95.6354666}, {"type": "node", "id": 229068315, "lat": 30.6984745, "lon": -95.630958}, {"type": "node", "id": 229069301, "lat": 30.6968451, "lon": -95.639395}, {"type": "node", "id": 229069344, "lat": 30.6963094, "lon": -95.6421908}, {"type": "node", "id": 229069388, "lat": 30.6957688, "lon": -95.6449285}, {"type": "node", "id": 229075427, "lat": 30.6739423, "lon": -95.7826793}, {"type": "node", "id": 229082941, "lat": 30.6844106, "lon": -95.7173553}, {"type": "node", "id": 229089635, "lat": 30.6952463, "lon": -95.6476441}, {"type": "node", "id": 229093253, "lat": 30.6609171, "lon": -95.8248569}, {"type": "node", "id": 229093663, "lat": 30.6670875, "lon": -95.8049153}, {"type": "node", "id": 229095111, "lat": 30.6958271, "lon": -95.6446047}, {"type": "node", "id": 229106619, "lat": 30.6722878, "lon": -95.788066}, {"type": "node", "id": 229106646, "lat": 30.6843951, "lon": -95.7204797}, {"type": "node", "id": 229107970, "lat": 30.699035, "lon": -95.628042}, {"type": "node", "id": 229110812, "lat": 30.6848325, "lon": -95.7016246}, {"type": "node", "id": 229112129, "lat": 30.6844272, "lon": -95.7123265}, {"type": "node", "id": 229123764, "lat": 30.6799296, "lon": -95.7635112}, {"type": "node", "id": 229125365, "lat": 30.6725626, "lon": -95.7871936}, {"type": "node", "id": 229125591, "lat": 30.6943987, "lon": -95.6520237}, {"type": "node", "id": 229125811, "lat": 30.6876743, "lon": -95.6867671}, {"type": "node", "id": 229126551, "lat": 30.684309, "lon": -95.7389446}, {"type": "node", "id": 229126754, "lat": 30.658167, "lon": -95.8337349}, {"type": "node", "id": 229126756, "lat": 30.6623726, "lon": -95.8201574}, {"type": "node", "id": 229126759, "lat": 30.668674, "lon": -95.7997689}, {"type": "node", "id": 229126763, "lat": 30.6710625, "lon": -95.7920226}, {"type": "node", "id": 229126767, "lat": 30.6769995, "lon": -95.7728937}, {"type": "node", "id": 229126779, "lat": 30.6796926, "lon": -95.7642861}, {"type": "node", "id": 229126783, "lat": 30.6840329, "lon": -95.7503153}, {"type": "node", "id": 229126787, "lat": 30.6842772, "lon": -95.7486997}, {"type": "node", "id": 229126790, "lat": 30.6843022, "lon": -95.7437202}, {"type": "node", "id": 229126796, "lat": 30.6843407, "lon": -95.7301649}, {"type": "node", "id": 229126799, "lat": 30.6844322, "lon": -95.7046183}, {"type": "node", "id": 229126802, "lat": 30.6861496, "lon": -95.6947441}, {"type": "node", "id": 229126805, "lat": 30.6885188, "lon": -95.682378}, {"type": "node", "id": 229126808, "lat": 30.689359, "lon": -95.678025}, {"type": "node", "id": 229126818, "lat": 30.689611, "lon": -95.6767}, {"type": "node", "id": 229126822, "lat": 30.6906069, "lon": -95.6715402}, {"type": "node", "id": 229126826, "lat": 30.6906971, "lon": -95.6710688}, {"type": "node", "id": 229126832, "lat": 30.6919276, "lon": -95.6646897}, {"type": "node", "id": 229126836, "lat": 30.6928953, "lon": -95.6598113}, {"type": "node", "id": 229126840, "lat": 30.695463, "lon": -95.6465128}, {"type": "node", "id": 229126846, "lat": 30.6954809, "lon": -95.646408}, {"type": "node", "id": 250552650, "lat": 30.6993711, "lon": -95.626203}, {"type": "node", "id": 1073587098, "lat": 30.5946456, "lon": -96.0877974}, {"type": "node", "id": 1073587121, "lat": 30.5946748, "lon": -96.088113}, {"type": "node", "id": 1073587125, "lat": 30.5946328, "lon": -96.0855818}, {"type": "node", "id": 1073587141, "lat": 30.5947332, "lon": -96.0886167}, {"type": "node", "id": 1073587254, "lat": 30.5946318, "lon": -96.0874477}, {"type": "node", "id": 1073587379, "lat": 30.5946418, "lon": -96.0835944}, {"type": "node", "id": 1073587428, "lat": 30.5947651, "lon": -96.0888341}, {"type": "node", "id": 1073587478, "lat": 30.5946365, "lon": -96.084367}, {"type": "node", "id": 1073587508, "lat": 30.5948152, "lon": -96.0891025}, {"type": "node", "id": 1073587535, "lat": 30.5947014, "lon": -96.0883655}, {"type": "node", "id": 1073932955, "lat": 30.603697, "lon": -96.1731173}, {"type": "node", "id": 1073932961, "lat": 30.6039634, "lon": -96.1738684}, {"type": "node", "id": 1073932963, "lat": 30.6034666, "lon": -96.1715289}, {"type": "node", "id": 1073932965, "lat": 30.6034813, "lon": -96.172001}, {"type": "node", "id": 1124053629, "lat": 30.5015749, "lon": -95.9915353}, {"type": "node", "id": 1124053630, "lat": 30.5210135, "lon": -95.9882843}, {"type": "node", "id": 1124053631, "lat": 30.4573006, "lon": -96.0244145}, {"type": "node", "id": 1124053632, "lat": 30.451405, "lon": -96.0270957}, {"type": "node", "id": 1124053633, "lat": 30.5008377, "lon": -95.991487}, {"type": "node", "id": 1124053634, "lat": 30.4083467, "lon": -96.0511465}, {"type": "node", "id": 1124053635, "lat": 30.5221697, "lon": -95.9877597}, {"type": "node", "id": 1124053636, "lat": 30.4442286, "lon": -96.0281672}, {"type": "node", "id": 1124053637, "lat": 30.4586013, "lon": -96.0233281}, {"type": "node", "id": 1124053638, "lat": 30.4270402, "lon": -96.0433123}, {"type": "node", "id": 1124053639, "lat": 30.4838255, "lon": -95.9942616}, {"type": "node", "id": 1124053640, "lat": 30.4530247, "lon": -96.0266422}, {"type": "node", "id": 1124053641, "lat": 30.4478317, "lon": -96.0269661}, {"type": "node", "id": 1124053642, "lat": 30.4009211, "lon": -96.0603712}, {"type": "node", "id": 1124053644, "lat": 30.4845618, "lon": -95.9925038}, {"type": "node", "id": 1124053645, "lat": 30.4473284, "lon": -96.0269811}, {"type": "node", "id": 1124053646, "lat": 30.5019747, "lon": -95.9915004}, {"type": "node", "id": 1124053647, "lat": 30.406438, "lon": -96.0524174}, {"type": "node", "id": 1124053648, "lat": 30.5203236, "lon": -95.9884787}, {"type": "node", "id": 1124053649, "lat": 30.4882693, "lon": -95.9876118}, {"type": "node", "id": 1124053650, "lat": 30.4857404, "lon": -95.9908014}, {"type": "node", "id": 1124053651, "lat": 30.4498401, "lon": -96.0271505}, {"type": "node", "id": 1124074212, "lat": 30.6822465, "lon": -95.9729766}, {"type": "node", "id": 1124074223, "lat": 30.658249, "lon": -95.9643464}, {"type": "node", "id": 1124074226, "lat": 30.585882, "lon": -95.9436687}, {"type": "node", "id": 1124074229, "lat": 30.6551331, "lon": -95.9602796}, {"type": "node", "id": 1124074233, "lat": 30.6014965, "lon": -95.9493273}, {"type": "node", "id": 1124074239, "lat": 30.5882603, "lon": -95.9438978}, {"type": "node", "id": 1124074242, "lat": 30.7682306, "lon": -95.9501805}, {"type": "node", "id": 1124074246, "lat": 30.683936, "lon": -95.9729554}, {"type": "node", "id": 1124074255, "lat": 30.6647992, "lon": -95.9646817}, {"type": "node", "id": 1124074256, "lat": 30.586839, "lon": -95.9436055}, {"type": "node", "id": 1124074258, "lat": 30.6557104, "lon": -95.9608781}, {"type": "node", "id": 1124074260, "lat": 30.6584952, "lon": -95.96441}, {"type": "node", "id": 1124074261, "lat": 30.6658222, "lon": -95.9650511}, {"type": "node", "id": 1124074263, "lat": 30.649831, "lon": -95.957775}, {"type": "node", "id": 1124074267, "lat": 30.6018064, "lon": -95.9493909}, {"type": "node", "id": 1124074281, "lat": 30.6561477, "lon": -95.9615786}, {"type": "node", "id": 1124074285, "lat": 30.76576, "lon": -95.9504267}, {"type": "node", "id": 1124074287, "lat": 30.6834605, "lon": -95.9730191}, {"type": "node", "id": 1124074290, "lat": 30.6549463, "lon": -95.9601055}, {"type": "node", "id": 1124074292, "lat": 30.6587924, "lon": -95.9644313}, {"type": "node", "id": 1124074294, "lat": 30.5877764, "lon": -95.943745}, {"type": "node", "id": 1124074296, "lat": 30.71889, "lon": -95.9633827}, {"type": "node", "id": 1124074298, "lat": 30.6653256, "lon": -95.9648515}, {"type": "node", "id": 1124074309, "lat": 30.6493853, "lon": -95.9576816}, {"type": "node", "id": 1124074311, "lat": 30.6027361, "lon": -95.949565}, {"type": "node", "id": 1124074314, "lat": 30.6559651, "lon": -95.9612687}, {"type": "node", "id": 1262082580, "lat": 30.6022099, "lon": -96.1102914}, {"type": "node", "id": 1262082581, "lat": 30.6050969, "lon": -96.1375797}, {"type": "node", "id": 1262082583, "lat": 30.6048875, "lon": -96.1359052}, {"type": "node", "id": 1262082585, "lat": 30.6022181, "lon": -96.1094371}, {"type": "node", "id": 1262082588, "lat": 30.6077904, "lon": -96.1821729}, {"type": "node", "id": 1262082590, "lat": 30.6018601, "lon": -96.1069233}, {"type": "node", "id": 1262082603, "lat": 30.6017055, "lon": -96.119094}, {"type": "node", "id": 1262082605, "lat": 30.6016486, "lon": -96.1062643}, {"type": "node", "id": 1262127231, "lat": 30.5997889, "lon": -95.9163225}, {"type": "node", "id": 1262127232, "lat": 30.6282452, "lon": -95.8808769}, {"type": "node", "id": 1262127233, "lat": 30.5875238, "lon": -95.9320024}, {"type": "node", "id": 1262127243, "lat": 30.6142971, "lon": -95.8864577}, {"type": "node", "id": 1262127244, "lat": 30.6444882, "lon": -95.8540422}, {"type": "node", "id": 1262127245, "lat": 30.5903155, "lon": -95.925752}, {"type": "node", "id": 1262127247, "lat": 30.5835898, "lon": -95.9392352}, {"type": "node", "id": 1262127251, "lat": 30.6382178, "lon": -95.8598972}, {"type": "node", "id": 1262127254, "lat": 30.5898082, "lon": -95.9262911}, {"type": "node", "id": 1262127255, "lat": 30.6287364, "lon": -95.8800183}, {"type": "node", "id": 1262127256, "lat": 30.6584575, "lon": -95.8328068}, {"type": "node", "id": 1262127257, "lat": 30.5845284, "lon": -95.9352933}, {"type": "node", "id": 1262127258, "lat": 30.603631, "lon": -95.9053713}, {"type": "node", "id": 1262127259, "lat": 30.6490692, "lon": -95.8514182}, {"type": "node", "id": 1262127260, "lat": 30.5932549, "lon": -95.9233916}, {"type": "node", "id": 1262127262, "lat": 30.5835459, "lon": -95.9396506}, {"type": "node", "id": 1262127263, "lat": 30.6032516, "lon": -95.90621}, {"type": "node", "id": 1262127264, "lat": 30.6138873, "lon": -95.8867353}, {"type": "node", "id": 1262127265, "lat": 30.6397115, "lon": -95.8583276}, {"type": "node", "id": 1262127267, "lat": 30.5876995, "lon": -95.9317108}, {"type": "node", "id": 1262127268, "lat": 30.6527275, "lon": -95.8451159}, {"type": "node", "id": 1262127269, "lat": 30.6112792, "lon": -95.8927547}, {"type": "node", "id": 1262127270, "lat": 30.6267515, "lon": -95.8822149}, {"type": "node", "id": 1262127271, "lat": 30.5852113, "lon": -95.9343987}, {"type": "node", "id": 1262127272, "lat": 30.6262203, "lon": -95.8824425}, {"type": "node", "id": 1262127274, "lat": 30.6038706, "lon": -95.9049679}, {"type": "node", "id": 1262127275, "lat": 30.5881388, "lon": -95.9305526}, {"type": "node", "id": 1262127276, "lat": 30.6174617, "lon": -95.8855338}, {"type": "node", "id": 1262127277, "lat": 30.6493967, "lon": -95.8510867}, {"type": "node", "id": 1262127278, "lat": 30.5839492, "lon": -95.936799}, {"type": "node", "id": 1262127279, "lat": 30.627678, "lon": -95.8815519}, {"type": "node", "id": 1262127280, "lat": 30.5835499, "lon": -95.9406051}, {"type": "node", "id": 1262127281, "lat": 30.5956414, "lon": -96.0325224}, {"type": "node", "id": 1262127282, "lat": 30.5992937, "lon": -95.9171212}, {"type": "node", "id": 1262127283, "lat": 30.613735, "lon": -95.8869647}, {"type": "node", "id": 1262127285, "lat": 30.5891013, "lon": -95.9590386}, {"type": "node", "id": 1262127286, "lat": 30.6325226, "lon": -95.8694625}, {"type": "node", "id": 1262127287, "lat": 30.5870724, "lon": -95.9326214}, {"type": "node", "id": 1262127288, "lat": 30.6499878, "lon": -95.8503119}, {"type": "node", "id": 1262127290, "lat": 30.5842807, "lon": -95.9357845}, {"type": "node", "id": 1262127291, "lat": 30.5893889, "lon": -95.9269741}, {"type": "node", "id": 1262157745, "lat": 30.6842057, "lon": -95.7495129}, {"type": "node", "id": 1262157750, "lat": 30.6845232, "lon": -95.7033486}, {"type": "node", "id": 1262157752, "lat": 30.6844529, "lon": -95.7041168}, {"type": "node", "id": 1329338648, "lat": 30.6314069, "lon": -96.2344221}, {"type": "node", "id": 1683641098, "lat": 30.6594524, "lon": -95.9643256}, {"type": "node", "id": 1683641162, "lat": 30.6133147, "lon": -95.887901, "tags": {"railway": "level_crossing"}}, {"type": "node", "id": 2347540924, "lat": 30.486524, "lon": -95.9889126}, {"type": "node", "id": 2347540928, "lat": 30.4866778, "lon": -95.9885154}, {"type": "node", "id": 2347540931, "lat": 30.4870519, "lon": -95.9880259}, {"type": "node", "id": 2347540938, "lat": 30.4874466, "lon": -95.9877568}, {"type": "node", "id": 2374365487, "lat": 30.5848144, "lon": -95.9348598}, {"type": "node", "id": 3334864646, "lat": 30.4841362, "lon": -95.9936073}, {"type": "node", "id": 3334864647, "lat": 30.4839391, "lon": -95.9940488}, {"type": "node", "id": 3334864648, "lat": 30.48369, "lon": -95.9944903}, {"type": "node", "id": 3334864649, "lat": 30.4843757, "lon": -95.9929736}, {"type": "node", "id": 3334864650, "lat": 30.4844674, "lon": -95.9927385}, {"type": "node", "id": 3334864651, "lat": 30.4846836, "lon": -95.9922731}, {"type": "node", "id": 3334864664, "lat": 30.4862209, "lon": -95.9898815}, {"type": "node", "id": 3334864665, "lat": 30.4863159, "lon": -95.9896201}, {"type": "node", "id": 3334864666, "lat": 30.485868, "lon": -95.9905998}, {"type": "node", "id": 3902786622, "lat": 30.6129038, "lon": -96.1918597}, {"type": "node", "id": 3902786625, "lat": 30.6163533, "lon": -96.196974}, {"type": "node", "id": 3902786627, "lat": 30.6169674, "lon": -96.1978817}, {"type": "node", "id": 3902786648, "lat": 30.630577, "lon": -96.2143168}, {"type": "node", "id": 3902786649, "lat": 30.6310907, "lon": -96.2174688}, {"type": "node", "id": 4160521866, "lat": 30.6844396, "lon": -95.7068913}, {"type": "node", "id": 4160521867, "lat": 30.68444, "lon": -95.7075299}, {"type": "node", "id": 4160521868, "lat": 30.6844404, "lon": -95.7081522}, {"type": "node", "id": 4374862735, "lat": 30.5300034, "lon": -95.9822522}, {"type": "node", "id": 4496314698, "lat": 30.7910452, "lon": -95.9492423}, {"type": "node", "id": 4498041170, "lat": 30.4711103, "lon": -96.009009}, {"type": "node", "id": 4501809590, "lat": 30.6145371, "lon": -95.8863799}, {"type": "node", "id": 4501809591, "lat": 30.6141551, "lon": -95.8865261}, {"type": "node", "id": 4501809592, "lat": 30.6137985, "lon": -95.8868507}, {"type": "node", "id": 4501817765, "lat": 30.5011612, "lon": -95.9915272}, {"type": "node", "id": 4501817766, "lat": 30.4996544, "lon": -95.9911102}, {"type": "node", "id": 4502074472, "lat": 30.488785, "lon": -95.9877509}, {"type": "node", "id": 4636476951, "lat": 30.587949, "lon": -95.9310869}, {"type": "node", "id": 4770640348, "lat": 30.5946482, "lon": -96.0746957}, {"type": "node", "id": 4857992483, "lat": 30.6888603, "lon": -95.6806049}, {"type": "node", "id": 4857992484, "lat": 30.688166, "lon": -95.6842272}, {"type": "node", "id": 4857992485, "lat": 30.6865837, "lon": -95.692483}, {"type": "node", "id": 4857992486, "lat": 30.685593, "lon": -95.6976677}, {"type": "node", "id": 4857992487, "lat": 30.6847164, "lon": -95.7022356}, {"type": "node", "id": 4857992488, "lat": 30.6846472, "lon": -95.7026097}, {"type": "node", "id": 4857992489, "lat": 30.684578, "lon": -95.7029893}, {"type": "node", "id": 4857992490, "lat": 30.68448, "lon": -95.7037309}, {"type": "node", "id": 4857992491, "lat": 30.684254, "lon": -95.7491112}, {"type": "node", "id": 4857992492, "lat": 30.6841294, "lon": -95.7499199}, {"type": "node", "id": 5970065605, "lat": 30.4896199, "lon": -95.9880201}, {"type": "node", "id": 5970069575, "lat": 30.4948816, "lon": -95.9889222}, {"type": "node", "id": 5972912606, "lat": 30.5840083, "lon": -95.94432}, {"type": "node", "id": 5972912610, "lat": 30.5828984, "lon": -95.9447742}, {"type": "node", "id": 5972912837, "lat": 30.5852202, "lon": -95.9438541}, {"type": "node", "id": 5972912839, "lat": 30.5842995, "lon": -95.9433674}, {"type": "node", "id": 5972912854, "lat": 30.5840514, "lon": -95.9425151}, {"type": "node", "id": 5972986829, "lat": 30.6120129, "lon": -95.8910459}, {"type": "node", "id": 5972986833, "lat": 30.6133555, "lon": -95.8878137}, {"type": "node", "id": 6979634019, "lat": 30.4642337, "lon": -96.0169289}, {"type": "node", "id": 7018729919, "lat": 30.4356569, "lon": -96.0357531}, {"type": "node", "id": 7111543968, "lat": 30.434615, "lon": -96.036693}, {"type": "node", "id": 7129246876, "lat": 30.5947058, "lon": -96.0784832}, {"type": "node", "id": 7129246877, "lat": 30.5946177, "lon": -96.0788224}, {"type": "node", "id": 7129246878, "lat": 30.5946232, "lon": -96.0776212}, {"type": "node", "id": 7129246879, "lat": 30.5946198, "lon": -96.0786924}, {"type": "node", "id": 7129246880, "lat": 30.5946185, "lon": -96.077956}, {"type": "node", "id": 7129246881, "lat": 30.5947179, "lon": -96.0768451}, {"type": "node", "id": 7173294716, "lat": 30.5949971, "lon": -96.0807264}, {"type": "node", "id": 7173294717, "lat": 30.5946274, "lon": -96.0767122}, {"type": "node", "id": 7173294719, "lat": 30.5948734, "lon": -96.0806606}, {"type": "node", "id": 7173294720, "lat": 30.594733, "lon": -96.0804995}, {"type": "node", "id": 7173294721, "lat": 30.5947259, "lon": -96.0796036}, {"type": "node", "id": 7173294722, "lat": 30.5947119, "lon": -96.0789437}, {"type": "node", "id": 7173294723, "lat": 30.594773, "lon": -96.0805853}, {"type": "node", "id": 7173294724, "lat": 30.5949, "lon": -96.0807516}, {"type": "node", "id": 7173294725, "lat": 30.5948261, "lon": -96.0807891}, {"type": "node", "id": 7173294726, "lat": 30.5947569, "lon": -96.0808374}, {"type": "node", "id": 7173294727, "lat": 30.5947153, "lon": -96.0809608}, {"type": "node", "id": 7173294728, "lat": 30.5947107, "lon": -96.0812666}, {"type": "node", "id": 7173294729, "lat": 30.5947107, "lon": -96.0815563}, {"type": "node", "id": 7173294730, "lat": 30.5947107, "lon": -96.0818352}, {"type": "node", "id": 7173294731, "lat": 30.5947061, "lon": -96.0822161}, {"type": "node", "id": 7173294732, "lat": 30.5947107, "lon": -96.082495}, {"type": "node", "id": 7173294733, "lat": 30.5946397, "lon": -96.0825648}, {"type": "node", "id": 7203110881, "lat": 30.4043454, "lon": -96.0547915}, {"type": "node", "id": 7229316646, "lat": 30.4635377, "lon": -96.0177343}, {"type": "node", "id": 7232380706, "lat": 30.6088295, "lon": -95.9506173}, {"type": "node", "id": 7249169809, "lat": 30.6035489, "lon": -96.1618487}, {"type": "node", "id": 7372378185, "lat": 30.5143636, "lon": -95.9894505}, {"type": "node", "id": 7377588490, "lat": 30.40325, "lon": -96.0563374}, {"type": "node", "id": 7377588500, "lat": 30.4033399, "lon": -96.0562019}, {"type": "node", "id": 7383812245, "lat": 30.4016931, "lon": -96.0588513}, {"type": "node", "id": 7384653513, "lat": 30.4046144, "lon": -96.0544206}, {"type": "node", "id": 7391666344, "lat": 30.3994281, "lon": -96.0644067}, {"type": "node", "id": 7400780747, "lat": 30.448656, "lon": -96.0270245}, {"type": "node", "id": 7401160166, "lat": 30.4096058, "lon": -96.0504878}, {"type": "node", "id": 7401160174, "lat": 30.4085974, "lon": -96.0510141}, {"type": "node", "id": 7401160176, "lat": 30.4091452, "lon": -96.0507249}, {"type": "node", "id": 7459344838, "lat": 30.6792266, "lon": -95.9718636}, {"type": "node", "id": 7459344861, "lat": 30.6841539, "lon": -95.9729137}, {"type": "node", "id": 7664127358, "lat": 30.4598928, "lon": -96.0218714}, {"type": "node", "id": 7677192126, "lat": 30.5946272, "lon": -96.0762111}, {"type": "node", "id": 7719616518, "lat": 30.4112893, "lon": -96.0497268}, {"type": "node", "id": 7733344904, "lat": 30.6130582, "lon": -95.951358}, {"type": "node", "id": 7738806506, "lat": 30.6803697, "lon": -95.9724567}, {"type": "node", "id": 7845161077, "lat": 30.6017782, "lon": -95.9105676}, {"type": "node", "id": 7845176789, "lat": 30.601971, "lon": -95.9099965}, {"type": "node", "id": 7908184072, "lat": 30.6273407, "lon": -96.2088242}, {"type": "node", "id": 8021753452, "lat": 30.6081816, "lon": -95.8980708}, {"type": "node", "id": 8021753475, "lat": 30.6071099, "lon": -95.8997811}, {"type": "node", "id": 8035367942, "lat": 30.5984934, "lon": -96.0986395}, {"type": "node", "id": 8076227704, "lat": 30.4303713, "lon": -96.0404556}, {"type": "node", "id": 8076260027, "lat": 30.4316904, "lon": -96.0392875}, {"type": "node", "id": 8095759359, "lat": 30.6017174, "lon": -96.1189078}, {"type": "node", "id": 8110521254, "lat": 30.6144161, "lon": -95.9516038}, {"type": "node", "id": 8153319229, "lat": 30.4869488, "lon": -95.9881282}, {"type": "node", "id": 8153319236, "lat": 30.4871511, "lon": -95.9879505}, {"type": "node", "id": 8154328760, "lat": 30.5946657, "lon": -96.0729157}, {"type": "node", "id": 8154328769, "lat": 30.5970371, "lon": -96.0950864}, {"type": "node", "id": 8190360052, "lat": 30.4051174, "lon": -96.0537131}, {"type": "node", "id": 8288855522, "lat": 30.5929612, "lon": -96.0005872}, {"type": "node", "id": 8314810117, "lat": 30.6873613, "lon": -95.6884074}, {"type": "node", "id": 8317263477, "lat": 30.5950781, "lon": -96.0901167}, {"type": "node", "id": 8348441873, "lat": 30.6020064, "lon": -96.1139164}, {"type": "node", "id": 8359924047, "lat": 30.6017196, "lon": -96.1188729}, {"type": "node", "id": 8373812771, "lat": 30.597519, "lon": -96.0962639}, {"type": "node", "id": 8374054324, "lat": 30.6844164, "lon": -95.7155983}, {"type": "node", "id": 8387228364, "lat": 30.6090826, "lon": -95.8966626}, {"type": "node", "id": 8531005680, "lat": 30.6210545, "lon": -95.9527636}, {"type": "node", "id": 8532520068, "lat": 30.6038492, "lon": -96.1547847}, {"type": "node", "id": 8549657545, "lat": 30.7652322, "lon": -95.9505668}, {"type": "node", "id": 8559134667, "lat": 30.5913285, "lon": -95.982382}, {"type": "node", "id": 8629087839, "lat": 30.4613067, "lon": -96.0202668}, {"type": "node", "id": 8651166508, "lat": 30.7728483, "lon": -95.950062}, {"type": "node", "id": 8692917362, "lat": 30.7972152, "lon": -95.9488902}, {"type": "node", "id": 8765190279, "lat": 30.6040148, "lon": -96.1525588}, {"type": "node", "id": 9018730053, "lat": 30.5841444, "lon": -95.9428312}, {"type": "way", "id": 20923619, "nodes": [224779761, 5970065605, 224756741, 224779766], "tags": {"highway": "primary", "ref": "TX 90; FM 149", "tiger:name_base_1": "State Highway 90"}}, {"type": "way", "id": 20923756, "nodes": [224781238, 224766201, 224781242], "tags": {"highway": "primary", "ref": "TX 90/FM 1696", "tiger:name_base_1": "State Highway 90"}}, {"type": "way", "id": 20924689, "nodes": [222638307, 224734270, 1073932961, 1073932955, 224789284, 224704961, 1073932965, 1073932963, 224789289, 224789291], "tags": {"Texas_Trunk_System": "yes", "highway": "primary", "lanes": "2", "maxspeed": "70 mph", "old_ref": "FM 158", "oneway": "no", "ref": "TX 30", "source:Texas_Trunk_System": "Statewide Long-Range Transportation Plan 2035 http://www.txdot.gov/txdot_library/publications/transportation_plan.htm", "tiger:cfcc": "A31", "tiger:county": "Grimes, TX", "tiger:name_base": "State Highway 30", "tiger:name_base_1": "Road 7873"}}, {"type": "way", "id": 20926104, "nodes": [224781238, 224773562, 224766147, 224751075, 224800847, 224802136, 4496314698, 224801375, 224801236, 8692917362, 224802140, 224755653, 224770976, 224710249, 224733538, 224717336, 224802167, 224802172, 224800644, 224774881, 224799797, 224802174, 224802176, 224785957, 224802180], "tags": {"highway": "primary", "ref": "TX 90", "tiger:cfcc": "A31", "tiger:county": "Grimes, TX", "tiger:name_base": "State Highway 90"}}, {"type": "way", "id": 20926127, "nodes": [224708201, 5970069575, 224802196, 224758491, 4501817766, 224758506, 224747886, 1124053633, 4501817765, 1124053629, 1124053646, 224733367, 224712171, 224735825, 224802231, 224774539, 224802240, 224736487, 224739516, 7372378185, 224802244, 224802246, 1124053648, 1124053630, 224802250, 224736513, 1124053635, 224802252, 224802257, 224736547, 224784051, 224736617, 4374862735, 224712159, 224736669, 224708482, 224718453, 224708556, 224768367, 224734493, 224794498, 224731583, 224752067, 224731645, 224731620, 224795466, 224731522, 224748090, 224802277, 224712143, 224770068, 224712136, 224756345, 224756379, 224802286, 224771797, 224802290, 5972912610, 224773886, 5972912606, 224789414], "tags": {"highway": "primary", "oneway": "no", "ref": "TX 90", "tiger:cfcc": "A31", "tiger:county": "Grimes, TX", "tiger:name_base": "State Highway 90"}}, {"type": "way", "id": 20926132, "nodes": [224779766, 224802580, 224802586, 224788097, 224708201], "tags": {"highway": "primary", "ref": "TX 90", "tiger:cfcc": "A31", "tiger:county": "Grimes, TX", "tiger:name_base": "State Highway 90", "tiger:separated": "no", "tiger:source": "tiger_import_dch_v0.6_20070829", "tiger:tlid": "21908487:21890869:21910066:21903856", "tiger:upload_uuid": "bulk_upload.pl-39170e2a-8a82-493a-883e-e4adc3885c0a"}}, {"type": "way", "id": 20926142, "nodes": [224764280, 224712269, 224802598, 7391666344, 224703843, 224738461, 224746723, 1124053642, 224727666, 224738594, 224802605, 7383812245, 224727719, 224802608, 7377588490, 224716227, 7377588500, 224727760, 224802611, 7203110881, 7384653513, 224724975, 8190360052, 224698147, 224802614, 224787801, 224802616, 1124053647, 224802619, 224767888, 1124053634, 7401160174, 7401160176, 224785988, 7401160166, 224802625, 7719616518, 224802628, 224743764, 224802631, 224741051, 224738358, 224802639, 224751468, 224737702, 224802656, 224780372, 1124053638, 224802660, 224802664, 224736045, 8076227704, 8076260027, 224802668, 224746934, 7111543968, 224746604, 7018729919, 224743362, 224802688, 1124053636, 224802691, 224780884, 224802694, 224802698, 224786132, 224802701, 1124053645, 1124053641, 224802704, 7400780747, 1124053651, 224802707, 1124053632, 224802713, 1124053640, 224786149, 224802724, 1124053631, 224802728, 1124053637, 224776171, 7664127358, 8629087839, 224744425, 7229316646, 6979634019, 224744348, 224744331, 4498041170, 224774576, 224779112, 224802756, 224802757, 3334864648, 1124053639, 3334864647, 224802758, 3334864646, 224788847, 3334864649, 3334864650, 1124053644, 3334864651, 224802759, 224773698, 224802760, 1124053650, 3334864666, 224802761, 3334864664, 3334864665, 224786984, 2347540924, 2347540928, 224759536, 8153319229, 2347540931, 8153319236, 224756796, 2347540938, 224802762, 224768707, 1124053649, 224768708], "tags": {"highway": "primary", "name": "State Highway 90", "ref": "TX 90"}}, {"type": "way", "id": 21300702, "nodes": [224789655, 229126754, 1262127256, 229032643, 229093253, 229126756, 229036830, 229027768, 229036900, 229093663, 229126759, 229032617, 229126763, 229106619, 229125365, 229075427, 229038410, 229126767, 229035541, 229045382, 229126779, 229123764, 229032566, 229126783, 4857992492, 1262157745, 4857992491, 229126787, 229126790, 229056381, 229126551, 229032656, 229126796, 229056518, 229106646, 229082941, 8374054324, 229112129, 4160521868, 4160521867, 4160521866, 229126799, 1262157752, 4857992490, 1262157750, 4857992489, 4857992488, 4857992487, 229110812, 4857992486, 229126802, 4857992485, 8314810117, 229125811, 4857992484, 229126805, 4857992483, 229126808, 229126818, 229028889, 229126822, 229126826, 229126832, 229126836, 229125591, 229089635, 229126840, 229126846, 229069388, 229095111, 229069344, 229069301, 229068269, 229068315, 229107970, 250552650], "tags": {"Texas_Trunk_System": "yes", "highway": "primary", "lanes": "2", "maxspeed": "70 mph", "old_ref": "SH 45", "oneway": "no", "ref": "TX 30", "source:Texas_Trunk_System": "Statewide Long-Range Transportation Plan 2035 http://www.txdot.gov/txdot_library/publications/transportation_plan.htm", "tiger:cfcc": "A31", "tiger:county": "Walker, TX", "tiger:name_base": "State Highway 30"}}, {"type": "way", "id": 92478917, "nodes": [224789348, 1073587125], "tags": {"Texas_Trunk_System": "yes", "bridge": "yes", "highway": "primary", "lanes": "2", "layer": "1", "old_ref": "FM 158", "ref": "TX 30", "source:Texas_Trunk_System": "Statewide Long-Range Transportation Plan 2035 http://www.txdot.gov/txdot_library/publications/transportation_plan.htm", "tiger:cfcc": "A31", "tiger:county": "Grimes, TX", "tiger:name_base": "State Highway 30", "tiger:name_base_1": "Road 7873", "tiger:separated": "no", "tiger:source": "tiger_import_dch_v0.6_20070829", "tiger:tlid": "21906003:21905806:21906001:21897530:21897534:21897624:21897619:21897535:21897526:21897253:21897061:21897059:21905820:21902360:21905819:21901625:21897700:21897698:21898110:21898112:21898103:21897703:21897706:21906620:21897714:21897718:21897709:21906601:219", "tiger:upload_uuid": "bulk_upload.pl-39170e2a-8a82-493a-883e-e4adc3885c0a"}}, {"type": "way", "id": 92478938, "nodes": [4770640348, 8154328760, 224772640, 224789361, 224789365, 224745910, 224733738, 224745978, 224789367, 224720037, 1262127281, 224789373, 224789376, 224745996, 224775143, 224721245, 224721168, 224716608, 224725662, 224773406, 224789381, 8288855522, 224789386, 224708461, 224773385, 224706701, 8559134667, 224789392, 224726111, 224743800, 224789398, 224789402, 1262127285, 224789405, 224789408, 224743678, 224715949, 224773896, 224789414], "tags": {"Texas_Trunk_System": "yes", "highway": "primary", "lanes": "2", "maxspeed": "70 mph", "old_ref": "FM 158", "oneway": "no", "ref": "TX 30", "source:Texas_Trunk_System": "Statewide Long-Range Transportation Plan 2035 http://www.txdot.gov/txdot_library/publications/transportation_plan.htm", "surface": "asphalt", "tiger:cfcc": "A31", "tiger:county": "Grimes, TX", "tiger:name_base": "State Highway 30", "tiger:name_base_1": "Road 7873"}}, {"type": "way", "id": 110534063, "nodes": [1262082588, 222638307], "tags": {"bridge": "yes", "highway": "primary", "lanes": "2", "layer": "1", "old_ref": "FM 158", "ref": "TX 30", "tiger:cfcc": "A31", "tiger:county": "Brazos, TX", "tiger:name_base": "State Highway 30", "tiger:zip_left": "77845", "tiger:zip_right": "77845"}}, {"type": "way", "id": 118135556, "nodes": [1329338648, 222469125, 222638100, 222638116, 222469502, 222638130, 222638135, 3902786649, 3902786648, 222638139, 222638144, 222638146, 222638147, 222638151, 222638154, 222638159, 222638164, 222638168, 222638174, 222638181, 222638185, 7908184072, 222638210, 222638213, 222638219, 222566673, 222638231, 222638235, 222638239, 222638245, 222638250, 222638254, 222638255, 222638259, 222554292, 3902786627], "tags": {"highway": "primary", "lanes": "2", "old_ref": "FM 158", "oneway": "no", "ref": "TX 30", "tiger:cfcc": "A31", "tiger:county": "Brazos, TX", "tiger:name_base": "State Highway 30", "tiger:zip_left": "77845", "tiger:zip_right": "77845"}}, {"type": "way", "id": 125985769, "nodes": [224789414, 5972912837, 224802293, 1124074226, 224802296, 1124074256, 224802299, 1124074294, 1124074239, 224802307, 224751534, 224802332, 224743634, 224795560, 224802352, 1124074233, 1124074267, 1124074311, 224743596, 224802365, 7232380706, 224749012, 224792067, 7733344904, 224799034, 8110521254, 224802375, 8531005680, 224802389, 224740304, 224802398, 224802401, 224802413, 224767227, 1124074309, 1124074263, 224776455, 224760945, 224762416, 224802421, 224802422, 224767697, 1124074290, 1124074229, 224802423, 1124074258, 1124074314, 1124074281, 224802427, 224802430, 224802432, 224802436, 224696691, 224802440, 1124074223, 1124074260, 1124074292, 224802444, 1683641098], "tags": {"highway": "primary", "oneway": "no", "ref": "TX 90", "tiger:cfcc": "A31", "tiger:county": "Grimes, TX", "tiger:name_base": "State Highway 90"}}, {"type": "way", "id": 144881147, "nodes": [224789414, 5972912839, 9018730053, 224789420, 5972912854, 224742381, 224789424, 1262127280, 224789428, 1262127262, 1262127247, 224789430, 1262127278, 224789434, 1262127290, 1262127257, 2374365487, 224761354, 1262127271, 224789438, 224789440, 1262127287, 224789446, 1262127233, 1262127267, 224789449, 4636476951, 1262127275, 224742195, 224789453, 1262127291, 224748802, 1262127254, 224789457, 1262127245, 224744545, 224789462, 224789465, 224789469, 1262127260, 224742068, 224721635, 224762166, 224725996, 224721867, 224789473, 1262127282, 224789477, 1262127231, 224789487, 7845161077, 7845176789, 224789496, 224696644, 1262127263, 224789498, 1262127258, 1262127274, 224789512, 224696564, 8021753475, 224732353, 8021753452, 8387228364, 224789521, 224758284, 224789529, 224758278, 1262127269, 224758235, 224758706, 5972986829, 224760094, 224782382, 224782921, 1683641162, 5972986833, 224735857], "tags": {"Texas_Trunk_System": "yes", "highway": "primary", "lanes": "2", "maxspeed": "65 mph", "old_ref": "SH 45", "oneway": "no", "ref": "TX 30", "source:Texas_Trunk_System": "Statewide Long-Range Transportation Plan 2035 http://www.txdot.gov/txdot_library/publications/transportation_plan.htm", "surface": "asphalt", "tiger:cfcc": "A31", "tiger:county": "Grimes, TX", "tiger:name_base": "State Highway 30", "tiger:name_base_1": "Road 7873"}}, {"type": "way", "id": 156059942, "nodes": [224802448, 224802452, 224726377, 224802456, 224755331, 224752446, 224802463, 1124074255, 1124074298, 1124074261, 224802466, 224751883, 224728796, 224721008, 7459344838, 7738806506, 224794756, 224802498, 224802501, 1124074212, 224802505, 1124074287, 1124074246, 7459344861, 224802508, 224802512, 224754455, 224749043, 224802515, 224748984, 224761947, 224710043, 224802519, 224773166, 224802523, 1124074296, 224802526, 224698684, 224714304, 224802530, 224751780, 224802543, 224761010, 224802546, 224802550, 224760922, 224697228, 224786255, 224802554, 8549657545, 1124074285, 224802558, 1124074242, 8651166508, 224781242], "tags": {"highway": "primary", "ref": "TX 90", "tiger:cfcc": "A31", "tiger:county": "Grimes, TX", "tiger:name_base": "State Highway 90"}}, {"type": "way", "id": 156059953, "nodes": [1683641098, 224802448], "tags": {"bridge": "yes", "highway": "primary", "layer": "1", "ref": "TX 90", "tiger:cfcc": "A31", "tiger:county": "Grimes, TX", "tiger:name_base": "State Highway 90", "tiger:separated": "no", "tiger:source": "tiger_import_dch_v0.6_20070829", "tiger:tlid": "21906806:21896845:21896464:21896866:21897092:21897464:21906848:21909519:21902731:21902732:21896907:21896931:21896919:21901035:21906861:21906862:21906865:21897165:21906867:21906060:21906061:21907254:21907255:21897281:21897190:21896991:21896995:21906057:219", "tiger:upload_uuid": "bulk_upload.pl-39170e2a-8a82-493a-883e-e4adc3885c0a"}}, {"type": "way", "id": 386919330, "nodes": [3902786627, 3902786625], "tags": {"bridge": "yes", "highway": "primary", "lanes": "2", "old_ref": "FM 158", "oneway": "no", "ref": "TX 30", "tiger:cfcc": "A31", "tiger:county": "Brazos, TX", "tiger:name_base": "State Highway 30", "tiger:zip_left": "77845", "tiger:zip_right": "77845"}}, {"type": "way", "id": 386919331, "nodes": [3902786622, 222638267], "tags": {"bridge": "yes", "highway": "primary", "lanes": "2", "layer": "1", "old_ref": "FM 158", "oneway": "no", "ref": "TX 30", "tiger:cfcc": "A31", "tiger:county": "Brazos, TX", "tiger:name_base": "State Highway 30", "tiger:zip_left": "77845", "tiger:zip_right": "77845"}}, {"type": "way", "id": 386919332, "nodes": [3902786625, 222476183, 3902786622], "tags": {"highway": "primary", "lanes": "2", "old_ref": "FM 158", "ref": "TX 30", "tiger:cfcc": "A31", "tiger:county": "Brazos, TX", "tiger:name_base": "State Highway 30", "tiger:zip_left": "77845", "tiger:zip_right": "77845"}}, {"type": "way", "id": 386919333, "nodes": [222638267, 222638269, 222638273, 222638279, 222638283, 222638286, 222638290, 1262082588], "tags": {"highway": "primary", "lanes": "2", "old_ref": "FM 158", "oneway": "no", "ref": "TX 30", "tiger:cfcc": "A31", "tiger:county": "Brazos, TX", "tiger:name_base": "State Highway 30", "tiger:zip_left": "77845", "tiger:zip_right": "77845"}}, {"type": "way", "id": 484317968, "nodes": [224774232, 7129246878, 224777855, 224715646, 7173294717, 7677192126, 224762765, 4770640348], "tags": {"Texas_Trunk_System": "yes", "highway": "primary", "lanes": "3", "lanes:backward": "2", "lanes:forward": "1", "maxspeed": "70 mph", "old_ref": "FM 158", "oneway": "no", "ref": "TX 30", "source:Texas_Trunk_System": "Statewide Long-Range Transportation Plan 2035 http://www.txdot.gov/txdot_library/publications/transportation_plan.htm", "surface": "asphalt", "tiger:cfcc": "A31", "tiger:county": "Grimes, TX", "tiger:name_base": "State Highway 30", "tiger:name_base_1": "Road 7873", "turn:lanes:backward": "left|"}}, {"type": "way", "id": 484317969, "nodes": [224766069, 7129246877], "tags": {"Texas_Trunk_System": "yes", "highway": "primary", "lanes": "2", "maxspeed": "70 mph", "old_ref": "FM 158", "ref": "TX 30", "source:Texas_Trunk_System": "Statewide Long-Range Transportation Plan 2035 http://www.txdot.gov/txdot_library/publications/transportation_plan.htm", "surface": "asphalt", "tiger:cfcc": "A31", "tiger:county": "Grimes, TX", "tiger:name_base": "State Highway 30", "tiger:name_base_1": "Road 7873"}}, {"type": "way", "id": 484317970, "nodes": [224724929, 224766069], "tags": {"Texas_Trunk_System": "yes", "highway": "primary", "lanes": "3", "lanes:backward": "1", "lanes:forward": "2", "maxspeed": "70 mph", "old_ref": "FM 158", "oneway": "no", "ref": "TX 30", "source:Texas_Trunk_System": "Statewide Long-Range Transportation Plan 2035 http://www.txdot.gov/txdot_library/publications/transportation_plan.htm", "surface": "asphalt", "tiger:cfcc": "A31", "tiger:county": "Grimes, TX", "tiger:name_base": "State Highway 30", "tiger:name_base_1": "Road 7873", "turn:lanes:forward": "left|"}}, {"type": "way", "id": 484317971, "nodes": [1073587125, 1073587478, 1073587379, 7173294733, 224724929], "tags": {"Texas_Trunk_System": "yes", "highway": "primary", "lanes": "2", "maxspeed": "70 mph", "old_ref": "FM 158", "oneway": "no", "ref": "TX 30", "source:Texas_Trunk_System": "Statewide Long-Range Transportation Plan 2035 http://www.txdot.gov/txdot_library/publications/transportation_plan.htm", "surface": "asphalt", "tiger:cfcc": "A31", "tiger:county": "Grimes, TX", "tiger:name_base": "State Highway 30", "tiger:name_base_1": "Road 7873"}}, {"type": "way", "id": 620757794, "nodes": [224768708, 4502074472, 224779761], "tags": {"highway": "primary", "name": "State Highway 90", "ref": "TX 90"}}, {"type": "way", "id": 632609005, "nodes": [224735857, 1262127283, 4501809592, 1262127264, 224697904, 4501809591, 1262127243, 4501809590, 224789551, 224749309, 224723902, 1262127276, 224789558, 224724760, 224739204, 1262127272, 224745215, 1262127270, 224745093, 224789574, 1262127279, 224789577, 1262127232, 224789582, 1262127255, 224789587, 224789595, 224708603, 224789600, 224789605, 1262127286, 224789609, 224789614, 224777121, 1262127251, 224789619, 1262127265, 224789623, 224718627, 224789625, 1262127244, 224716269, 224789629, 1262127259, 1262127277, 224789633, 1262127288, 224789635, 224789640, 1262127268, 224789643, 224783380, 224789651, 224789655], "tags": {"Texas_Trunk_System": "yes", "highway": "primary", "lanes": "2", "maxspeed": "70 mph", "old_ref": "SH 45", "oneway": "no", "ref": "TX 30", "source:Texas_Trunk_System": "Statewide Long-Range Transportation Plan 2035 http://www.txdot.gov/txdot_library/publications/transportation_plan.htm", "surface": "asphalt", "tiger:cfcc": "A31", "tiger:county": "Grimes, TX", "tiger:name_base": "State Highway 30", "tiger:name_base_1": "Road 7873"}}, {"type": "way", "id": 762950945, "nodes": [7129246877, 7129246879, 7129246880, 224774232], "tags": {"Texas_Trunk_System": "yes", "highway": "primary", "lanes": "2", "maxspeed": "70 mph", "old_ref": "FM 158", "oneway": "no", "ref": "TX 30"}}, {"type": "way", "id": 762950946, "nodes": [7173294717, 7129246881, 7129246876, 7173294722, 7173294721, 7173294720, 7173294723, 7173294719, 7173294716], "tags": {"Texas_Trunk_System": "yes", "highway": "primary", "lanes": "2", "maxspeed": "70 mph", "old_ref": "FM 158", "oneway": "yes", "ref": "FM 244", "source:Texas_Trunk_System": "Statewide Long-Range Transportation Plan 2035 http://www.txdot.gov/txdot_library/publications/transportation_plan.htm", "surface": "asphalt", "tiger:cfcc": "A31", "tiger:county": "Grimes, TX", "tiger:name_base": "State Highway 30", "tiger:name_base_1": "Road 7873"}}, {"type": "way", "id": 768330540, "nodes": [7173294716, 7173294724, 7173294725, 7173294726, 7173294727, 7173294728, 7173294729, 7173294730, 7173294731, 7173294732, 7173294733], "tags": {"Texas_Trunk_System": "yes", "highway": "primary", "lanes": "2", "maxspeed": "70 mph", "old_ref": "FM 158", "oneway": "yes", "ref": "TX 30", "source:Texas_Trunk_System": "Statewide Long-Range Transportation Plan 2035 http://www.txdot.gov/txdot_library/publications/transportation_plan.htm", "surface": "asphalt", "tiger:cfcc": "A31", "tiger:county": "Grimes, TX", "tiger:name_base": "State Highway 30", "tiger:name_base_1": "Road 7873"}}, {"type": "way", "id": 776905349, "nodes": [224789291, 7249169809], "tags": {"Texas_Trunk_System": "yes", "bridge": "yes", "highway": "primary", "lanes": "2", "layer": "1", "old_ref": "FM 158", "ref": "TX 30", "source:Texas_Trunk_System": "Statewide Long-Range Transportation Plan 2035 http://www.txdot.gov/txdot_library/publications/transportation_plan.htm", "tiger:cfcc": "A31", "tiger:county": "Grimes, TX", "tiger:name_base": "State Highway 30", "tiger:name_base_1": "Road 7873"}}, {"type": "way", "id": 776905350, "nodes": [7249169809, 224789293, 224707368, 8532520068, 8765190279, 224707832, 224789302, 224789311, 1262082581, 224733876, 1262082583, 224789313, 224789317, 224789319, 224715993, 224734811, 224772654, 1262082603, 8095759359, 8359924047, 224731971, 224766580, 8348441873, 1262082580, 1262082585, 224789323, 224789325, 1262082590, 1262082605, 224789329, 224789335, 8035367942, 224696575, 8373812771, 8154328769, 224789340, 8317263477, 224789344, 224771103, 1073587508, 1073587428, 1073587141, 1073587535, 1073587121, 1073587098, 1073587254, 224789348], "tags": {"Texas_Trunk_System": "yes", "highway": "primary", "lanes": "2", "maxspeed": "70 mph", "old_ref": "FM 158", "oneway": "no", "ref": "TX 30", "source:Texas_Trunk_System": "Statewide Long-Range Transportation Plan 2035 http://www.txdot.gov/txdot_library/publications/transportation_plan.htm", "tiger:cfcc": "A31", "tiger:county": "Grimes, TX", "tiger:name_base": "State Highway 30", "tiger:name_base_1": "Road 7873"}}]}