{"version": 0.6, "generator": "Overpass API 0.7.56.9 76e5016d", "osm3s": {"timestamp_osm_base": "2021-08-30T15:33:59Z", "copyright": "The data included in this document is from www.openstreetmap.org. The data is made available under ODbL."}, "elements": [{"type": "node", "id": 260403334, "lat": -16.8511955, "lon": -49.4100539}, {"type": "node", "id": 260403340, "lat": -16.8515168, "lon": -49.410465}, {"type": "node", "id": 260403344, "lat": -16.8519399, "lon": -49.4110803}, {"type": "node", "id": 260403345, "lat": -16.8523004, "lon": -49.4117665}, {"type": "node", "id": 260403347, "lat": -16.8525853, "lon": -49.4126786}, {"type": "node", "id": 260403349, "lat": -16.8527245, "lon": -49.4135743}, {"type": "node", "id": 260403351, "lat": -16.853312, "lon": -49.4184108}, {"type": "node", "id": 260403353, "lat": -16.853517, "lon": -49.4193299}, {"type": "node", "id": 260403355, "lat": -16.8538524, "lon": -49.4201463}, {"type": "node", "id": 260403357, "lat": -16.8542818, "lon": -49.4208682}, {"type": "node", "id": 260403359, "lat": -16.854751, "lon": -49.4214536}, {"type": "node", "id": 260403362, "lat": -16.8554822, "lon": -49.4221234}, {"type": "node", "id": 260403363, "lat": -16.8655705, "lon": -49.4310315}, {"type": "node", "id": 260403365, "lat": -16.8688545, "lon": -49.4338179}, {"type": "node", "id": 260403381, "lat": -16.8716717, "lon": -49.434762}, {"type": "node", "id": 260403383, "lat": -16.8768732, "lon": -49.4360524}, {"type": "node", "id": 260403385, "lat": -16.888127, "lon": -49.4389075}, {"type": "node", "id": 260403387, "lat": -16.8969106, "lon": -49.4411389}, {"type": "node", "id": 260403390, "lat": -16.9028649, "lon": -49.4435719}, {"type": "node", "id": 260403394, "lat": -16.9036208, "lon": -49.4440044}, {"type": "node", "id": 260403405, "lat": -16.9163566, "lon": -49.4546102}, {"type": "node", "id": 260403407, "lat": -16.9216418, "lon": -49.4487326}, {"type": "node", "id": 260403408, "lat": -16.9232371, "lon": -49.4469307}, {"type": "node", "id": 260403410, "lat": -16.9247608, "lon": -49.4452163}, {"type": "node", "id": 260403412, "lat": -16.9259036, "lon": -49.4442023}, {"type": "node", "id": 340258290, "lat": -16.9188423, "lon": -49.3438925}, {"type": "node", "id": 340258291, "lat": -16.9182137, "lon": -49.3393059}, {"type": "node", "id": 340258292, "lat": -16.9179872, "lon": -49.3385965}, {"type": "node", "id": 340258293, "lat": -16.9177171, "lon": -49.338005}, {"type": "node", "id": 340258294, "lat": -16.9172564, "lon": -49.3372527}, {"type": "node", "id": 340258902, "lat": -16.9144139, "lon": -49.3328362}, {"type": "node", "id": 340258904, "lat": -16.914069, "lon": -49.3323984}, {"type": "node", "id": 340258906, "lat": -16.913601, "lon": -49.331995}, {"type": "node", "id": 340258918, "lat": -16.8982525, "lon": -49.3220129}, {"type": "node", "id": 340258920, "lat": -16.8975564, "lon": -49.3215537}, {"type": "node", "id": 340258921, "lat": -16.8970617, "lon": -49.321043}, {"type": "node", "id": 340258923, "lat": -16.8966018, "lon": -49.3204851}, {"type": "node", "id": 340258924, "lat": -16.8944747, "lon": -49.3176785}, {"type": "node", "id": 340258926, "lat": -16.8927336, "lon": -49.3154554}, {"type": "node", "id": 340258928, "lat": -16.8900891, "lon": -49.3122797}, {"type": "node", "id": 340258931, "lat": -16.8812108, "lon": -49.3014822}, {"type": "node", "id": 340259300, "lat": -16.8788372, "lon": -49.2985897}, {"type": "node", "id": 340259301, "lat": -16.874721, "lon": -49.2934786}, {"type": "node", "id": 340259302, "lat": -16.8741391, "lon": -49.2926502}, {"type": "node", "id": 340259303, "lat": -16.8736956, "lon": -49.2918434}, {"type": "node", "id": 340259304, "lat": -16.8733342, "lon": -49.2910452}, {"type": "node", "id": 340259305, "lat": -16.8728824, "lon": -49.289835}, {"type": "node", "id": 340259306, "lat": -16.8718274, "lon": -49.2866715}, {"type": "node", "id": 340259307, "lat": -16.8711576, "lon": -49.2850199}, {"type": "node", "id": 340259308, "lat": -16.8691042, "lon": -49.2805309}, {"type": "node", "id": 340259309, "lat": -16.8689727, "lon": -49.2801704}, {"type": "node", "id": 340259311, "lat": -16.8663667, "lon": -49.2648238}, {"type": "node", "id": 340259316, "lat": -16.8587432, "lon": -49.2567773}, {"type": "node", "id": 340259317, "lat": -16.8580974, "lon": -49.2567387}, {"type": "node", "id": 340259318, "lat": -16.8571656, "lon": -49.2565208}, {"type": "node", "id": 340259319, "lat": -16.8565367, "lon": -49.2562666}, {"type": "node", "id": 340259320, "lat": -16.8523307, "lon": -49.254637}, {"type": "node", "id": 340259345, "lat": -16.8495955, "lon": -49.2535715}, {"type": "node", "id": 340259346, "lat": -16.8492176, "lon": -49.2534771}, {"type": "node", "id": 340259349, "lat": -16.8459811, "lon": -49.2528505}, {"type": "node", "id": 340259922, "lat": -16.845595, "lon": -49.2527132}, {"type": "node", "id": 340259923, "lat": -16.8452007, "lon": -49.25249}, {"type": "node", "id": 340259925, "lat": -16.842843, "lon": -49.2505245}, {"type": "node", "id": 340259926, "lat": -16.8417422, "lon": -49.2496147}, {"type": "node", "id": 340259927, "lat": -16.8405478, "lon": -49.249042}, {"type": "node", "id": 340259928, "lat": -16.835951, "lon": -49.2468908}, {"type": "node", "id": 340259929, "lat": -16.8356276, "lon": -49.2466565}, {"type": "node", "id": 340259930, "lat": -16.8344616, "lon": -49.246216}, {"type": "node", "id": 340260024, "lat": -16.8323623, "lon": -49.2457626}, {"type": "node", "id": 340260126, "lat": -16.8326177, "lon": -49.2456056}, {"type": "node", "id": 340260155, "lat": -16.8352898, "lon": -49.2444823}, {"type": "node", "id": 340260181, "lat": -16.8324624, "lon": -49.2456713}, {"type": "node", "id": 340337691, "lat": -16.8564742, "lon": -49.4642999}, {"type": "node", "id": 340337692, "lat": -16.8564167, "lon": -49.4636991}, {"type": "node", "id": 340337693, "lat": -16.8562935, "lon": -49.4631326}, {"type": "node", "id": 340337694, "lat": -16.8543878, "lon": -49.4570043}, {"type": "node", "id": 340337695, "lat": -16.8542481, "lon": -49.4563348}, {"type": "node", "id": 340337696, "lat": -16.8541816, "lon": -49.4556727}, {"type": "node", "id": 340337697, "lat": -16.8541933, "lon": -49.4549084}, {"type": "node", "id": 340337698, "lat": -16.8545192, "lon": -49.4489791}, {"type": "node", "id": 340337699, "lat": -16.8546178, "lon": -49.4482152}, {"type": "node", "id": 340337700, "lat": -16.8548231, "lon": -49.4473398}, {"type": "node", "id": 340337701, "lat": -16.8564414, "lon": -49.4412973}, {"type": "node", "id": 340337702, "lat": -16.856811, "lon": -49.440439}, {"type": "node", "id": 340337703, "lat": -16.8574679, "lon": -49.4394076}, {"type": "node", "id": 340337704, "lat": -16.8578871, "lon": -49.4390056}, {"type": "node", "id": 340337705, "lat": -16.858651, "lon": -49.4383704}, {"type": "node", "id": 340337706, "lat": -16.8594724, "lon": -49.4378297}, {"type": "node", "id": 340337707, "lat": -16.8603431, "lon": -49.4374349}, {"type": "node", "id": 340337708, "lat": -16.8611481, "lon": -49.4372289}, {"type": "node", "id": 340337709, "lat": -16.8617642, "lon": -49.4371602}, {"type": "node", "id": 340337710, "lat": -16.8625527, "lon": -49.4371774}, {"type": "node", "id": 340337711, "lat": -16.8639573, "lon": -49.4373147}, {"type": "node", "id": 340337712, "lat": -16.8647212, "lon": -49.4373061}, {"type": "node", "id": 340337713, "lat": -16.8655312, "lon": -49.4372005}, {"type": "node", "id": 340337714, "lat": -16.8664965, "lon": -49.4369068}, {"type": "node", "id": 340337715, "lat": -16.8673661, "lon": -49.4364307}, {"type": "node", "id": 340337716, "lat": -16.8692901, "lon": -49.4350704}, {"type": "node", "id": 340337859, "lat": -16.8698597, "lon": -49.4342942}, {"type": "node", "id": 340337884, "lat": -16.8703644, "lon": -49.4343188}, {"type": "node", "id": 340337885, "lat": -16.8703143, "lon": -49.4342064}, {"type": "node", "id": 340337886, "lat": -16.8702275, "lon": -49.4341318}, {"type": "node", "id": 340337887, "lat": -16.8701188, "lon": -49.4341022}, {"type": "node", "id": 340337888, "lat": -16.8700082, "lon": -49.4341232}, {"type": "node", "id": 340337890, "lat": -16.8699158, "lon": -49.4341915}, {"type": "node", "id": 340337891, "lat": -16.8698362, "lon": -49.434432}, {"type": "node", "id": 340337892, "lat": -16.8698736, "lon": -49.4345147}, {"type": "node", "id": 340337893, "lat": -16.8700179, "lon": -49.4346015}, {"type": "node", "id": 340337894, "lat": -16.8700828, "lon": -49.434646}, {"type": "node", "id": 340337895, "lat": -16.870239, "lon": -49.4346111}, {"type": "node", "id": 340337896, "lat": -16.8702939, "lon": -49.4345671}, {"type": "node", "id": 340337897, "lat": -16.8703357, "lon": -49.4345097}, {"type": "node", "id": 340337898, "lat": -16.8703617, "lon": -49.4344428}, {"type": "node", "id": 340337908, "lat": -16.8699109, "lon": -49.4341287}, {"type": "node", "id": 340337909, "lat": -16.8698297, "lon": -49.4341372}, {"type": "node", "id": 340337911, "lat": -16.869645, "lon": -49.4341951}, {"type": "node", "id": 340337955, "lat": -16.8698283, "lon": -49.4346404}, {"type": "node", "id": 340337956, "lat": -16.8697513, "lon": -49.4347125}, {"type": "node", "id": 340337968, "lat": -16.8698049, "lon": -49.4343542}, {"type": "node", "id": 340337973, "lat": -16.870493, "lon": -49.4345565}, {"type": "node", "id": 340337974, "lat": -16.8707836, "lon": -49.4345332}, {"type": "node", "id": 340337976, "lat": -16.8699002, "lon": -49.4346999}, {"type": "node", "id": 340337980, "lat": -16.8705563, "lon": -49.4343499}, {"type": "node", "id": 340337981, "lat": -16.8704867, "lon": -49.4343031}, {"type": "node", "id": 589546287, "lat": -16.9295619, "lon": -49.4411675}, {"type": "node", "id": 589546291, "lat": -16.9396226, "lon": -49.4348779}, {"type": "node", "id": 589546294, "lat": -16.9428474, "lon": -49.4323195}, {"type": "node", "id": 589546296, "lat": -16.9446621, "lon": -49.4297925}, {"type": "node", "id": 589546299, "lat": -16.945979, "lon": -49.4269599}, {"type": "node", "id": 589546301, "lat": -16.9474757, "lon": -49.4253203}, {"type": "node", "id": 589546313, "lat": -16.9487194, "lon": -49.4248741}, {"type": "node", "id": 589546314, "lat": -16.9513689, "lon": -49.4262512}, {"type": "node", "id": 589546315, "lat": -16.955106, "lon": -49.4281579}, {"type": "node", "id": 589546317, "lat": -16.9594808, "lon": -49.4287352}, {"type": "node", "id": 589546320, "lat": -16.9638905, "lon": -49.4291377}, {"type": "node", "id": 589546323, "lat": -16.9729312, "lon": -49.4299589}, {"type": "node", "id": 589546326, "lat": -16.9768355, "lon": -49.430248}, {"type": "node", "id": 589546330, "lat": -16.9795103, "lon": -49.4295711}, {"type": "node", "id": 589546332, "lat": -16.9819985, "lon": -49.4287986}, {"type": "node", "id": 589546337, "lat": -16.9841256, "lon": -49.4286394}, {"type": "node", "id": 589546340, "lat": -16.9868765, "lon": -49.4298391}, {"type": "node", "id": 589546342, "lat": -16.9884686, "lon": -49.431703}, {"type": "node", "id": 589546346, "lat": -16.9918045, "lon": -49.4363376}, {"type": "node", "id": 589546348, "lat": -16.9945222, "lon": -49.4405616}, {"type": "node", "id": 589546351, "lat": -16.9970843, "lon": -49.4454524}, {"type": "node", "id": 589546355, "lat": -16.9993471, "lon": -49.4491845}, {"type": "node", "id": 589546357, "lat": -17.0033142, "lon": -49.451035}, {"type": "node", "id": 589546360, "lat": -17.0088043, "lon": -49.4522168}, {"type": "node", "id": 589546362, "lat": -17.0137211, "lon": -49.4511715}, {"type": "node", "id": 589546365, "lat": -17.0199709, "lon": -49.4493961}, {"type": "node", "id": 589546369, "lat": -17.0238505, "lon": -49.4483267}, {"type": "node", "id": 589546372, "lat": -17.0362507, "lon": -49.4438831}, {"type": "node", "id": 589546375, "lat": -17.0385354, "lon": -49.4433398}, {"type": "node", "id": 589546376, "lat": -17.0428268, "lon": -49.4398827}, {"type": "node", "id": 589546377, "lat": -17.0549194, "lon": -49.4320981}, {"type": "node", "id": 589546378, "lat": -17.0746705, "lon": -49.4210441}, {"type": "node", "id": 589546379, "lat": -17.0896243, "lon": -49.4053099}, {"type": "node", "id": 589546383, "lat": -17.1077436, "lon": -49.4040497}, {"type": "node", "id": 589546386, "lat": -17.1109706, "lon": -49.4043224}, {"type": "node", "id": 589546390, "lat": -17.1128881, "lon": -49.4054807}, {"type": "node", "id": 589546393, "lat": -17.1249288, "lon": -49.4168803}, {"type": "node", "id": 589546396, "lat": -17.1389891, "lon": -49.4317325}, {"type": "node", "id": 589546399, "lat": -17.1430447, "lon": -49.4349025}, {"type": "node", "id": 589546403, "lat": -17.1460865, "lon": -49.4352521}, {"type": "node", "id": 589546406, "lat": -17.1647675, "lon": -49.4297719}, {"type": "node", "id": 589546408, "lat": -17.1745948, "lon": -49.4335284}, {"type": "node", "id": 589546421, "lat": -17.1804326, "lon": -49.4320404}, {"type": "node", "id": 589546423, "lat": -17.2081899, "lon": -49.4205514}, {"type": "node", "id": 589546424, "lat": -17.2254085, "lon": -49.4225109}, {"type": "node", "id": 589546425, "lat": -17.2291945, "lon": -49.4206449}, {"type": "node", "id": 589546426, "lat": -17.2676637, "lon": -49.3952642}, {"type": "node", "id": 589546428, "lat": -17.2703307, "lon": -49.3947844}, {"type": "node", "id": 589546430, "lat": -17.2800204, "lon": -49.396805}, {"type": "node", "id": 589546672, "lat": -16.9495606, "lon": -49.4217954}, {"type": "node", "id": 589546673, "lat": -16.9496825, "lon": -49.4191091}, {"type": "node", "id": 589546676, "lat": -16.9497173, "lon": -49.41621}, {"type": "node", "id": 589546678, "lat": -16.948695, "lon": -49.412459}, {"type": "node", "id": 589546681, "lat": -16.9477348, "lon": -49.4097302}, {"type": "node", "id": 589546683, "lat": -16.9471739, "lon": -49.4067946}, {"type": "node", "id": 589546685, "lat": -16.9467411, "lon": -49.4030495}, {"type": "node", "id": 589546688, "lat": -16.9463021, "lon": -49.3993791}, {"type": "node", "id": 589546690, "lat": -16.9459022, "lon": -49.3990627}, {"type": "node", "id": 589546694, "lat": -16.9427429, "lon": -49.3971933}, {"type": "node", "id": 589546698, "lat": -16.9415511, "lon": -49.3955867}, {"type": "node", "id": 589546699, "lat": -16.9411028, "lon": -49.3932416}, {"type": "node", "id": 589546702, "lat": -16.9407621, "lon": -49.3919443}, {"type": "node", "id": 589546704, "lat": -16.9396447, "lon": -49.3902183}, {"type": "node", "id": 589546706, "lat": -16.9375753, "lon": -49.3878016}, {"type": "node", "id": 589546709, "lat": -16.9360746, "lon": -49.3849461}, {"type": "node", "id": 589546711, "lat": -16.9347439, "lon": -49.3823916}, {"type": "node", "id": 589546713, "lat": -16.932788, "lon": -49.3782395}, {"type": "node", "id": 589546715, "lat": -16.931633, "lon": -49.3764491}, {"type": "node", "id": 589546717, "lat": -16.9307185, "lon": -49.3756358}, {"type": "node", "id": 589546724, "lat": -16.9288392, "lon": -49.3743133}, {"type": "node", "id": 589546726, "lat": -16.9274703, "lon": -49.3728144}, {"type": "node", "id": 589546729, "lat": -16.9265696, "lon": -49.3707607}, {"type": "node", "id": 589546732, "lat": -16.925806, "lon": -49.3686353}, {"type": "node", "id": 589546735, "lat": -16.9256571, "lon": -49.3677024}, {"type": "node", "id": 589546737, "lat": -16.9255186, "lon": -49.3653099}, {"type": "node", "id": 589546740, "lat": -16.9257523, "lon": -49.3610835}, {"type": "node", "id": 589546743, "lat": -16.9259761, "lon": -49.3598449}, {"type": "node", "id": 589546744, "lat": -16.9264618, "lon": -49.3569366}, {"type": "node", "id": 589546748, "lat": -16.9271076, "lon": -49.3530965}, {"type": "node", "id": 589546752, "lat": -16.9254795, "lon": -49.350311}, {"type": "node", "id": 589546759, "lat": -16.9217895, "lon": -49.34956}, {"type": "node", "id": 589546762, "lat": -16.9207438, "lon": -49.3489552}, {"type": "node", "id": 589546764, "lat": -16.9191323, "lon": -49.3449413}, {"type": "node", "id": 765258748, "lat": -16.9194556, "lon": -49.4511741}, {"type": "node", "id": 765258760, "lat": -16.9206591, "lon": -49.4498069}, {"type": "node", "id": 765258782, "lat": -16.9183019, "lon": -49.4524552}, {"type": "node", "id": 765271327, "lat": -16.9181058, "lon": -49.4526574}, {"type": "node", "id": 765271340, "lat": -16.9041734, "lon": -49.4444734}, {"type": "node", "id": 765271349, "lat": -16.9170329, "lon": -49.4538587}, {"type": "node", "id": 765271480, "lat": -16.9177228, "lon": -49.4530914}, {"type": "node", "id": 1306302190, "lat": -16.8377347, "lon": -49.2477065}, {"type": "node", "id": 1306312585, "lat": -16.8667145, "lon": -49.2669838}, {"type": "node", "id": 1448720889, "lat": -17.2696281, "lon": -49.3947926}, {"type": "node", "id": 1448721006, "lat": -17.2644142, "lon": -49.3971912}, {"type": "node", "id": 1448721109, "lat": -17.2684634, "lon": -49.3949999}, {"type": "node", "id": 1448721133, "lat": -17.254747, "lon": -49.4030048}, {"type": "node", "id": 1448721195, "lat": -17.2690108, "lon": -49.3948739}, {"type": "node", "id": 1765483636, "lat": -16.86714, "lon": -49.4324434}, {"type": "node", "id": 1765483637, "lat": -16.8682744, "lon": -49.4334263}, {"type": "node", "id": 1771628573, "lat": -17.2807813, "lon": -49.3969717}, {"type": "node", "id": 2024048901, "lat": -16.8683923, "lon": -49.276795}, {"type": "node", "id": 2024048910, "lat": -16.8655227, "lon": -49.2590838}, {"type": "node", "id": 2024048913, "lat": -16.8642463, "lon": -49.2563354}, {"type": "node", "id": 2024048914, "lat": -16.8690149, "lon": -49.2802862}, {"type": "node", "id": 2024048918, "lat": -16.8724487, "lon": -49.2884925}, {"type": "node", "id": 2024048920, "lat": -16.868703, "lon": -49.2786095}, {"type": "node", "id": 2024048927, "lat": -16.8699367, "lon": -49.2823508}, {"type": "node", "id": 2024048965, "lat": -16.8695898, "lon": -49.2815926}, {"type": "node", "id": 2024048994, "lat": -16.8724897, "lon": -49.2885729}, {"type": "node", "id": 2024049007, "lat": -16.8654344, "lon": -49.2583829}, {"type": "node", "id": 2024049023, "lat": -16.8661659, "lon": -49.2633032}, {"type": "node", "id": 2024049030, "lat": -16.8666096, "lon": -49.2662872}, {"type": "node", "id": 2024049037, "lat": -16.8667054, "lon": -49.2669322}, {"type": "node", "id": 2024049084, "lat": -16.869289, "lon": -49.280935}, {"type": "node", "id": 2024049092, "lat": -16.8664894, "lon": -49.2655229}, {"type": "node", "id": 2024049107, "lat": -16.8663558, "lon": -49.2647362}, {"type": "node", "id": 2024049113, "lat": -16.8653508, "lon": -49.2577194}, {"type": "node", "id": 2024049117, "lat": -16.8662618, "lon": -49.2639778}, {"type": "node", "id": 2024049118, "lat": -16.8652853, "lon": -49.2569829}, {"type": "node", "id": 2505930182, "lat": -16.9447425, "lon": -49.3986623}, {"type": "node", "id": 2505930183, "lat": -16.9433962, "lon": -49.3980148}, {"type": "node", "id": 2505930184, "lat": -16.9422054, "lon": -49.3964115}, {"type": "node", "id": 2505930185, "lat": -16.9412611, "lon": -49.3948665}, {"type": "node", "id": 2505930186, "lat": -16.938449, "lon": -49.3890113}, {"type": "node", "id": 2505937998, "lat": -16.9416255, "lon": -49.3956953}, {"type": "node", "id": 2505938105, "lat": -16.8673716, "lon": -49.4326439}, {"type": "node", "id": 2868392850, "lat": -16.8377999, "lon": -49.3935755}, {"type": "node", "id": 2868392853, "lat": -16.838152, "lon": -49.3939657}, {"type": "node", "id": 2868392857, "lat": -16.8385767, "lon": -49.3944618}, {"type": "node", "id": 2868392860, "lat": -16.8390367, "lon": -49.3950194}, {"type": "node", "id": 2868392868, "lat": -16.8394975, "lon": -49.3956002}, {"type": "node", "id": 2868392872, "lat": -16.8399455, "lon": -49.3961628}, {"type": "node", "id": 2868392877, "lat": -16.8401956, "lon": -49.3964696}, {"type": "node", "id": 2868392880, "lat": -16.8405076, "lon": -49.3968417}, {"type": "node", "id": 2868392894, "lat": -16.8412786, "lon": -49.3978274}, {"type": "node", "id": 2868392916, "lat": -16.8425883, "lon": -49.3994372}, {"type": "node", "id": 2868392941, "lat": -16.8449373, "lon": -49.4023371}, {"type": "node", "id": 2982733648, "lat": -17.2809909, "lon": -49.3970245}, {"type": "node", "id": 2986286013, "lat": -16.8697508, "lon": -49.434296}, {"type": "node", "id": 2986286716, "lat": -16.870107, "lon": -49.4343657}, {"type": "node", "id": 2986286717, "lat": -16.8702289, "lon": -49.4344081}, {"type": "node", "id": 2986300441, "lat": -16.8669402, "lon": -49.4366874}, {"type": "node", "id": 2986300442, "lat": -16.8660054, "lon": -49.4370731}, {"type": "node", "id": 2986300443, "lat": -16.8651214, "lon": -49.4372643}, {"type": "node", "id": 2986313276, "lat": -16.9277674, "lon": -49.4426964}, {"type": "node", "id": 2986313277, "lat": -16.933178, "lon": -49.43869}, {"type": "node", "id": 2986313278, "lat": -16.9312773, "lon": -49.4398257}, {"type": "node", "id": 2986313279, "lat": -16.9351552, "lon": -49.4375221}, {"type": "node", "id": 2986313280, "lat": -16.9386831, "lon": -49.4354764}, {"type": "node", "id": 2986313281, "lat": -16.9415812, "lon": -49.4336573}, {"type": "node", "id": 2986313282, "lat": -16.944113, "lon": -49.4308227}, {"type": "node", "id": 2986313283, "lat": -16.9452986, "lon": -49.4283343}, {"type": "node", "id": 2986313284, "lat": -16.9467317, "lon": -49.4259885}, {"type": "node", "id": 2986314072, "lat": -16.9481162, "lon": -49.424469}, {"type": "node", "id": 2986314073, "lat": -16.9480673, "lon": -49.4245327}, {"type": "node", "id": 2986314074, "lat": -16.9480452, "lon": -49.4246109}, {"type": "node", "id": 2986314075, "lat": -16.948046, "lon": -49.4246582}, {"type": "node", "id": 2986314076, "lat": -16.9483331, "lon": -49.4248221}, {"type": "node", "id": 2986314077, "lat": -16.9484237, "lon": -49.4247336}, {"type": "node", "id": 2986314078, "lat": -16.9484447, "lon": -49.424675}, {"type": "node", "id": 2986314079, "lat": -16.9484312, "lon": -49.4245433}, {"type": "node", "id": 2986314080, "lat": -16.9480569, "lon": -49.4247042}, {"type": "node", "id": 2986314081, "lat": -16.9480923, "lon": -49.4247674}, {"type": "node", "id": 2986314082, "lat": -16.9481461, "lon": -49.4248143}, {"type": "node", "id": 2986314085, "lat": -16.94827, "lon": -49.4248409}, {"type": "node", "id": 2986314087, "lat": -16.9483926, "lon": -49.4244838}, {"type": "node", "id": 2986314088, "lat": -16.9483372, "lon": -49.4244413}, {"type": "node", "id": 2986314089, "lat": -16.9482619, "lon": -49.4244197}, {"type": "node", "id": 2986314090, "lat": -16.9481844, "lon": -49.4244293}, {"type": "node", "id": 2986314852, "lat": -16.9478697, "lon": -49.4249601}, {"type": "node", "id": 2986316278, "lat": -16.9494556, "lon": -49.4227955}, {"type": "node", "id": 2986316279, "lat": -16.949335, "lon": -49.4232346}, {"type": "node", "id": 2986316280, "lat": -16.9491639, "lon": -49.4236086}, {"type": "node", "id": 2986316281, "lat": -16.9486693, "lon": -49.4242156}, {"type": "node", "id": 2986421727, "lat": -16.9500233, "lon": -49.4255682}, {"type": "node", "id": 2986421728, "lat": -16.9493332, "lon": -49.425192}, {"type": "node", "id": 2986421729, "lat": -16.9489896, "lon": -49.4250105}, {"type": "node", "id": 2986421730, "lat": -16.953185, "lon": -49.4271862}, {"type": "node", "id": 2986421731, "lat": -16.9541377, "lon": -49.4276578}, {"type": "node", "id": 2986421732, "lat": -16.9572837, "lon": -49.4285644}, {"type": "node", "id": 2986421733, "lat": -16.9561754, "lon": -49.4284506}, {"type": "node", "id": 2986421734, "lat": -16.9617129, "lon": -49.4289425}, {"type": "node", "id": 2986421735, "lat": -16.9749026, "lon": -49.43015}, {"type": "node", "id": 2986421736, "lat": -16.9758706, "lon": -49.4302295}, {"type": "node", "id": 2986421737, "lat": -16.9781959, "lon": -49.4299979}, {"type": "node", "id": 2986421738, "lat": -16.9807623, "lon": -49.4291974}, {"type": "node", "id": 2986421739, "lat": -16.9830758, "lon": -49.4286091}, {"type": "node", "id": 2986421740, "lat": -16.9825392, "lon": -49.4286724}, {"type": "node", "id": 2986421741, "lat": -16.9852374, "lon": -49.4288942}, {"type": "node", "id": 2986421742, "lat": -16.9860744, "lon": -49.4292585}, {"type": "node", "id": 2986421743, "lat": -16.9877453, "lon": -49.4307297}, {"type": "node", "id": 2986421744, "lat": -16.9872283, "lon": -49.43015}, {"type": "node", "id": 2986421745, "lat": -16.9900977, "lon": -49.4339674}, {"type": "node", "id": 2986421746, "lat": -16.9909842, "lon": -49.4351993}, {"type": "node", "id": 2986421747, "lat": -16.9932897, "lon": -49.4384069}, {"type": "node", "id": 2986421748, "lat": -16.9959335, "lon": -49.4430416}, {"type": "node", "id": 2986421749, "lat": -16.997928, "lon": -49.4474363}, {"type": "node", "id": 2986421750, "lat": -16.9984918, "lon": -49.4484446}, {"type": "node", "id": 2986421751, "lat": -16.9981846, "lon": -49.4479648}, {"type": "node", "id": 2986421752, "lat": -16.9983246, "lon": -49.4482006}, {"type": "node", "id": 2986421753, "lat": -16.9989116, "lon": -49.4488552}, {"type": "node", "id": 2986421754, "lat": -17.0012182, "lon": -49.4503876}, {"type": "node", "id": 2986421755, "lat": -17.0022513, "lon": -49.4507903}, {"type": "node", "id": 2986421756, "lat": -17.0062737, "lon": -49.4517274}, {"type": "node", "id": 2986421757, "lat": -17.0073442, "lon": -49.451925}, {"type": "node", "id": 2986421758, "lat": -17.0080673, "lon": -49.4520854}, {"type": "node", "id": 2986421759, "lat": -17.0112749, "lon": -49.4518695}, {"type": "node", "id": 2986421760, "lat": -17.010063, "lon": -49.4521565}, {"type": "node", "id": 2986421761, "lat": -17.0094253, "lon": -49.45222}, {"type": "node", "id": 2986421763, "lat": -17.0269907, "lon": -49.4471548}, {"type": "node", "id": 2986421764, "lat": -17.0255221, "lon": -49.4478305}, {"type": "node", "id": 2986421765, "lat": -17.0248403, "lon": -49.4480513}, {"type": "node", "id": 2986421766, "lat": -17.0292694, "lon": -49.445936}, {"type": "node", "id": 2986421767, "lat": -17.0281304, "lon": -49.446546}, {"type": "node", "id": 2986421768, "lat": -17.0275629, "lon": -49.4468509}, {"type": "node", "id": 2986421769, "lat": -17.0278389, "lon": -49.4467086}, {"type": "node", "id": 2986421770, "lat": -17.0327004, "lon": -49.4448106}, {"type": "node", "id": 2986421771, "lat": -17.0309603, "lon": -49.4451898}, {"type": "node", "id": 2986421772, "lat": -17.0300992, "lon": -49.4455071}, {"type": "node", "id": 2986421773, "lat": -17.030607, "lon": -49.4452985}, {"type": "node", "id": 2986421774, "lat": -17.0345132, "lon": -49.4443222}, {"type": "node", "id": 2986421775, "lat": -17.040748, "lon": -49.4418219}, {"type": "node", "id": 2986421776, "lat": -17.0397611, "lon": -49.4427115}, {"type": "node", "id": 2986421777, "lat": -17.0392165, "lon": -49.4430741}, {"type": "node", "id": 2986421778, "lat": -17.0417703, "lon": -49.4408706}, {"type": "node", "id": 2986421779, "lat": -17.0438554, "lon": -49.4389273}, {"type": "node", "id": 2986421780, "lat": -17.0455484, "lon": -49.4373255}, {"type": "node", "id": 2986421781, "lat": -17.0482808, "lon": -49.4357034}, {"type": "node", "id": 2986421782, "lat": -17.046901, "lon": -49.4364311}, {"type": "node", "id": 2986421783, "lat": -17.0462014, "lon": -49.4368336}, {"type": "node", "id": 2986421784, "lat": -17.0506335, "lon": -49.4344697}, {"type": "node", "id": 2986421785, "lat": -17.052704, "lon": -49.4333084}, {"type": "node", "id": 2986421786, "lat": -17.0553469, "lon": -49.4318674}, {"type": "node", "id": 2986421787, "lat": -17.0584667, "lon": -49.4302368}, {"type": "node", "id": 2986421788, "lat": -17.0609553, "lon": -49.4288445}, {"type": "node", "id": 2986421789, "lat": -17.0637268, "lon": -49.427357}, {"type": "node", "id": 2986421790, "lat": -17.0662577, "lon": -49.4259829}, {"type": "node", "id": 2986421791, "lat": -17.0686216, "lon": -49.4247196}, {"type": "node", "id": 2986421792, "lat": -17.0718374, "lon": -49.4229866}, {"type": "node", "id": 2986421793, "lat": -17.0733258, "lon": -49.4221735}, {"type": "node", "id": 2986421794, "lat": -17.073988, "lon": -49.4216934}, {"type": "node", "id": 2986421795, "lat": -17.0766564, "lon": -49.4188203}, {"type": "node", "id": 2986421796, "lat": -17.0830103, "lon": -49.4117171}, {"type": "node", "id": 2986421797, "lat": -17.079777, "lon": -49.4154004}, {"type": "node", "id": 2986421798, "lat": -17.086224, "lon": -49.4080867}, {"type": "node", "id": 2986421799, "lat": -17.0877202, "lon": -49.4064076}, {"type": "node", "id": 2986421800, "lat": -17.0885984, "lon": -49.4056758}, {"type": "node", "id": 2986421801, "lat": -17.0881398, "lon": -49.4060255}, {"type": "node", "id": 2986421802, "lat": -17.0928496, "lon": -49.4053628}, {"type": "node", "id": 2986421803, "lat": -17.0912603, "lon": -49.405253}, {"type": "node", "id": 2986421804, "lat": -17.0904481, "lon": -49.4052083}, {"type": "node", "id": 2986421805, "lat": -17.0900362, "lon": -49.4052408}, {"type": "node", "id": 2986421806, "lat": -17.0953132, "lon": -49.4053872}, {"type": "node", "id": 2986421807, "lat": -17.0940931, "lon": -49.4054278}, {"type": "node", "id": 2986421808, "lat": -17.0946954, "lon": -49.405436}, {"type": "node", "id": 2986421809, "lat": -17.0965723, "lon": -49.4051433}, {"type": "node", "id": 2986421810, "lat": -17.0994555, "lon": -49.4045294}, {"type": "node", "id": 2986421811, "lat": -17.1026146, "lon": -49.4041635}, {"type": "node", "id": 2986421812, "lat": -17.1010253, "lon": -49.4042936}, {"type": "node", "id": 2986421813, "lat": -17.1052025, "lon": -49.4041066}, {"type": "node", "id": 2986421814, "lat": -17.1038969, "lon": -49.4041554}, {"type": "node", "id": 2986421815, "lat": -17.1065158, "lon": -49.4041188}, {"type": "node", "id": 2986421816, "lat": -17.1094261, "lon": -49.4040334}, {"type": "node", "id": 2986421817, "lat": -17.110211, "lon": -49.4041228}, {"type": "node", "id": 2986421818, "lat": -17.1120061, "lon": -49.4048221}, {"type": "node", "id": 2986421819, "lat": -17.1189053, "lon": -49.4108596}, {"type": "node", "id": 2986421820, "lat": -17.1159421, "lon": -49.4082777}, {"type": "node", "id": 2986421821, "lat": -17.1220343, "lon": -49.4138921}, {"type": "node", "id": 2986421822, "lat": -17.1204001, "lon": -49.4122003}, {"type": "node", "id": 2986421823, "lat": -17.1236234, "lon": -49.4154817}, {"type": "node", "id": 2986421824, "lat": -17.1296765, "lon": -49.4217263}, {"type": "node", "id": 2986421825, "lat": -17.1343502, "lon": -49.4266333}, {"type": "node", "id": 2986421826, "lat": -17.132027, "lon": -49.4241209}, {"type": "node", "id": 2986421827, "lat": -17.133208, "lon": -49.4253446}, {"type": "node", "id": 2986421828, "lat": -17.1365258, "lon": -49.4292312}, {"type": "node", "id": 2986421829, "lat": -17.1376913, "lon": -49.4306053}, {"type": "node", "id": 2986421830, "lat": -17.1409547, "lon": -49.4333129}, {"type": "node", "id": 2986421831, "lat": -17.1446247, "lon": -49.4354271}, {"type": "node", "id": 2986421832, "lat": -17.1436467, "lon": -49.4351999}, {"type": "node", "id": 2986421933, "lat": -17.1453139, "lon": -49.4353942}, {"type": "node", "id": 2986421934, "lat": -17.1473957, "lon": -49.4348415}, {"type": "node", "id": 2986421935, "lat": -17.1507832, "lon": -49.433817}, {"type": "node", "id": 2986421936, "lat": -17.1533432, "lon": -49.4330771}, {"type": "node", "id": 2986421937, "lat": -17.1536501, "lon": -49.4329795}, {"type": "node", "id": 2986421938, "lat": -17.1582649, "lon": -49.4315647}, {"type": "node", "id": 2986421939, "lat": -17.1615318, "lon": -49.4306094}, {"type": "node", "id": 2986421940, "lat": -17.1631477, "lon": -49.4300808}, {"type": "node", "id": 2986421941, "lat": -17.1679605, "lon": -49.430585}, {"type": "node", "id": 2986421942, "lat": -17.1663756, "lon": -49.4299386}, {"type": "node", "id": 2986421943, "lat": -17.1671642, "lon": -49.4302272}, {"type": "node", "id": 2986421944, "lat": -17.1655638, "lon": -49.4297881}, {"type": "node", "id": 2986421945, "lat": -17.1639596, "lon": -49.4298735}, {"type": "node", "id": 2986421946, "lat": -17.171165, "lon": -49.4321014}, {"type": "node", "id": 2986421947, "lat": -17.1728352, "lon": -49.4328454}, {"type": "node", "id": 2986421948, "lat": -17.1736975, "lon": -49.433256}, {"type": "node", "id": 2986421949, "lat": -17.1777021, "lon": -49.4332031}, {"type": "node", "id": 2986421950, "lat": -17.176164, "lon": -49.4336178}, {"type": "node", "id": 2986421951, "lat": -17.1753716, "lon": -49.4336259}, {"type": "node", "id": 2986421952, "lat": -17.1769369, "lon": -49.4334714}, {"type": "node", "id": 2986421953, "lat": -17.1790615, "lon": -49.432634}, {"type": "node", "id": 2986421954, "lat": -17.1940489, "lon": -49.4261989}, {"type": "node", "id": 2986421955, "lat": -17.2011258, "lon": -49.4231736}, {"type": "node", "id": 2986421956, "lat": -17.2045705, "lon": -49.4216938}, {"type": "node", "id": 2986421957, "lat": -17.2063569, "lon": -49.4209457}, {"type": "node", "id": 2986421958, "lat": -17.2072579, "lon": -49.4206612}, {"type": "node", "id": 2986421959, "lat": -17.2146248, "lon": -49.4213401}, {"type": "node", "id": 2986421960, "lat": -17.2198633, "lon": -49.422015}, {"type": "node", "id": 2986421961, "lat": -17.2222127, "lon": -49.4223199}, {"type": "node", "id": 2986421962, "lat": -17.223696, "lon": -49.4224947}, {"type": "node", "id": 2986421963, "lat": -17.2246241, "lon": -49.4225719}, {"type": "node", "id": 2986421964, "lat": -17.2241581, "lon": -49.4225516}, {"type": "node", "id": 2986421965, "lat": -17.2274083, "lon": -49.4217792}, {"type": "node", "id": 2986421966, "lat": -17.2264453, "lon": -49.4222467}, {"type": "node", "id": 2986421967, "lat": -17.2269346, "lon": -49.4220434}, {"type": "node", "id": 2986421968, "lat": -17.2259211, "lon": -49.4224093}, {"type": "node", "id": 2986421969, "lat": -17.2343123, "lon": -49.4172746}, {"type": "node", "id": 2986421970, "lat": -17.2365915, "lon": -49.4157419}, {"type": "node", "id": 2986421971, "lat": -17.2386456, "lon": -49.4144247}, {"type": "node", "id": 2986421972, "lat": -17.2432972, "lon": -49.4112333}, {"type": "node", "id": 2986421973, "lat": -17.2411888, "lon": -49.4127213}, {"type": "node", "id": 2986421974, "lat": -17.2495949, "lon": -49.4066841}, {"type": "node", "id": 2986421975, "lat": -17.2521651, "lon": -49.4048505}, {"type": "node", "id": 2986421976, "lat": -17.2595884, "lon": -49.4000939}, {"type": "node", "id": 2986421977, "lat": -17.2620111, "lon": -49.3986426}, {"type": "node", "id": 2986421978, "lat": -17.2660525, "lon": -49.3962114}, {"type": "node", "id": 2986421979, "lat": -17.273386, "lon": -49.3953658}, {"type": "node", "id": 2986421980, "lat": -17.2718603, "lon": -49.3950324}, {"type": "node", "id": 2986421981, "lat": -17.2710839, "lon": -49.3948861}, {"type": "node", "id": 2986421982, "lat": -17.2726173, "lon": -49.3952113}, {"type": "node", "id": 2986423031, "lat": -17.1142905, "lon": -49.406765}, {"type": "node", "id": 2986427970, "lat": -17.1158377, "lon": -49.4081821}, {"type": "node", "id": 2986427991, "lat": -17.1166196, "lon": -49.4088788}, {"type": "node", "id": 2986429325, "lat": -17.1149817, "lon": -49.407398}, {"type": "node", "id": 2986430212, "lat": -17.1171231, "lon": -49.4093255}, {"type": "node", "id": 2986430565, "lat": -17.1175937, "lon": -49.4097412}, {"type": "node", "id": 2986434868, "lat": -17.118325, "lon": -49.4103918}, {"type": "node", "id": 3126429950, "lat": -16.8360455, "lon": -49.2462601}, {"type": "node", "id": 3126429954, "lat": -16.8355488, "lon": -49.2458425}, {"type": "node", "id": 3135514077, "lat": -16.8359386, "lon": -49.3914049}, {"type": "node", "id": 3135648576, "lat": -16.8973478, "lon": -49.4412583}, {"type": "node", "id": 3135648589, "lat": -16.8981541, "lon": -49.4415433}, {"type": "node", "id": 3135648615, "lat": -16.899614, "lon": -49.442169}, {"type": "node", "id": 3135648620, "lat": -16.9005406, "lon": -49.4425689}, {"type": "node", "id": 3135648621, "lat": -16.9008775, "lon": -49.3234583}, {"type": "node", "id": 3135648622, "lat": -16.900869, "lon": -49.3234896}, {"type": "node", "id": 3135648623, "lat": -16.901041, "lon": -49.3234541}, {"type": "node", "id": 3135648624, "lat": -16.9009935, "lon": -49.3235892}, {"type": "node", "id": 3135648625, "lat": -16.9010505, "lon": -49.3234823}, {"type": "node", "id": 3135648628, "lat": -16.9010513, "lon": -49.3235123}, {"type": "node", "id": 3135648835, "lat": -16.902066, "lon": -49.3241813}, {"type": "node", "id": 3135648837, "lat": -16.9021087, "lon": -49.3240998}, {"type": "node", "id": 3135648850, "lat": -16.9032757, "lon": -49.324848}, {"type": "node", "id": 3135648852, "lat": -16.9033123, "lon": -49.324767}, {"type": "node", "id": 3135648858, "lat": -16.9044493, "lon": -49.3254948}, {"type": "node", "id": 3135648860, "lat": -16.9044929, "lon": -49.3254215}, {"type": "node", "id": 3135648875, "lat": -16.9056227, "lon": -49.3261415}, {"type": "node", "id": 3135648877, "lat": -16.9056667, "lon": -49.3260722}, {"type": "node", "id": 3135648885, "lat": -16.9065472, "lon": -49.326651}, {"type": "node", "id": 3135648886, "lat": -16.9065829, "lon": -49.3265802}, {"type": "node", "id": 3135648890, "lat": -16.9069617, "lon": -49.3268795}, {"type": "node", "id": 3135648891, "lat": -16.9070008, "lon": -49.3268118}, {"type": "node", "id": 3135648896, "lat": -16.9075781, "lon": -49.3272192}, {"type": "node", "id": 3135648897, "lat": -16.9076223, "lon": -49.3271563}, {"type": "node", "id": 3135648901, "lat": -16.9091731, "lon": -49.3283593}, {"type": "node", "id": 3135648902, "lat": -16.9092145, "lon": -49.3282913}, {"type": "node", "id": 3135648909, "lat": -16.910737, "lon": -49.3296825}, {"type": "node", "id": 3135648910, "lat": -16.910784, "lon": -49.3296204}, {"type": "node", "id": 3135648919, "lat": -16.9121111, "lon": -49.3308286}, {"type": "node", "id": 3135648920, "lat": -16.9121643, "lon": -49.3307635}, {"type": "node", "id": 3135648921, "lat": -16.9122364, "lon": -49.330863}, {"type": "node", "id": 3135649092, "lat": -16.9203679, "lon": -49.4501348}, {"type": "node", "id": 3135649104, "lat": -16.9217164, "lon": -49.4486483}, {"type": "node", "id": 3135649368, "lat": -16.9267201, "lon": -49.3512847}, {"type": "node", "id": 3135649373, "lat": -16.926969, "lon": -49.3517661}, {"type": "node", "id": 3135649378, "lat": -16.927123, "lon": -49.3522704}, {"type": "node", "id": 3135649383, "lat": -16.9271281, "lon": -49.3526512}, {"type": "node", "id": 3135860552, "lat": -16.8335191, "lon": -49.2452126}, {"type": "node", "id": 3135860568, "lat": -16.8348921, "lon": -49.24563}, {"type": "node", "id": 3135860593, "lat": -16.8361241, "lon": -49.2460533}, {"type": "node", "id": 3135860762, "lat": -16.8436223, "lon": -49.2511907}, {"type": "node", "id": 3135860782, "lat": -16.8656276, "lon": -49.259772}, {"type": "node", "id": 3135860787, "lat": -16.8677775, "lon": -49.2732048}, {"type": "node", "id": 3135860792, "lat": -16.8688708, "lon": -49.2796066}, {"type": "node", "id": 3135899489, "lat": -16.8693309, "lon": -49.2810266}, {"type": "node", "id": 3146847935, "lat": -17.2665442, "lon": -49.3959151}, {"type": "node", "id": 3163960964, "lat": -16.9177424, "lon": -49.4530665}, {"type": "node", "id": 3183404877, "lat": -16.9335688, "lon": -49.3805491}, {"type": "node", "id": 3183404911, "lat": -16.9334002, "lon": -49.3801071}, {"type": "node", "id": 3183404934, "lat": -16.9254246, "lon": -49.3632993}, {"type": "node", "id": 3183405113, "lat": -16.9255468, "lon": -49.3659032}, {"type": "node", "id": 3183405144, "lat": -16.9322676, "lon": -49.3772935}, {"type": "node", "id": 3183405154, "lat": -16.9338641, "lon": -49.3811202}, {"type": "node", "id": 3183405158, "lat": -16.9298179, "lon": -49.3749589}, {"type": "node", "id": 3183405279, "lat": -16.9254944, "lon": -49.362618}, {"type": "node", "id": 3183405337, "lat": -16.9269727, "lon": -49.371862}, {"type": "node", "id": 3183405341, "lat": -16.9356265, "lon": -49.3839392}, {"type": "node", "id": 3183405349, "lat": -16.9254619, "lon": -49.3642719}, {"type": "node", "id": 3183405516, "lat": -16.9279758, "lon": -49.3735193}, {"type": "node", "id": 3854338362, "lat": -16.8359133, "lon": -49.2465252}, {"type": "node", "id": 3868769548, "lat": -16.8352871, "lon": -49.2445455}, {"type": "node", "id": 3916712956, "lat": -16.840426, "lon": -49.2489842}, {"type": "node", "id": 3916746914, "lat": -16.8382554, "lon": -49.2479615}, {"type": "node", "id": 3999141130, "lat": -16.8477372, "lon": -49.4058058}, {"type": "node", "id": 3999141132, "lat": -16.8505188, "lon": -49.4092222}, {"type": "node", "id": 3999141133, "lat": -16.8506404, "lon": -49.4094602}, {"type": "node", "id": 3999141134, "lat": -16.850693, "lon": -49.4095482}, {"type": "node", "id": 3999141135, "lat": -16.8507321, "lon": -49.409412}, {"type": "node", "id": 3999141136, "lat": -16.8507734, "lon": -49.4096718}, {"type": "node", "id": 3999141137, "lat": -16.8508248, "lon": -49.4095013}, {"type": "node", "id": 3999141138, "lat": -16.8509221, "lon": -49.4098288}, {"type": "node", "id": 3999141139, "lat": -16.8509347, "lon": -49.4096351}, {"type": "node", "id": 3999141140, "lat": -16.8510239, "lon": -49.4097728}, {"type": "node", "id": 3999141141, "lat": -16.8510615, "lon": -49.4099486}, {"type": "node", "id": 3999141142, "lat": -16.8517157, "lon": -49.410731}, {"type": "node", "id": 3999141143, "lat": -16.8524645, "lon": -49.4122228}, {"type": "node", "id": 3999141144, "lat": -16.8526679, "lon": -49.4131045}, {"type": "node", "id": 3999141145, "lat": -16.8533414, "lon": -49.4186574}, {"type": "node", "id": 3999141146, "lat": -16.8533876, "lon": -49.4188782}, {"type": "node", "id": 3999141147, "lat": -16.8538987, "lon": -49.4202485}, {"type": "node", "id": 3999141148, "lat": -16.8539515, "lon": -49.4203478}, {"type": "node", "id": 3999141149, "lat": -16.8540493, "lon": -49.4205231}, {"type": "node", "id": 3999141150, "lat": -16.8541589, "lon": -49.4206942}, {"type": "node", "id": 3999141151, "lat": -16.8551124, "lon": -49.4217954}, {"type": "node", "id": 3999141152, "lat": -16.8675541, "lon": -49.4328021}, {"type": "node", "id": 3999141153, "lat": -16.8706765, "lon": -49.434437}, {"type": "node", "id": 3999141154, "lat": -16.8825024, "lon": -49.4374779}, {"type": "node", "id": 3999141313, "lat": -16.9326631, "lon": -49.4389997}, {"type": "node", "id": 3999141320, "lat": -16.9478912, "lon": -49.4249143}, {"type": "node", "id": 3999141321, "lat": -16.9479264, "lon": -49.4249483}, {"type": "node", "id": 3999141322, "lat": -16.9479603, "lon": -49.4248347}, {"type": "node", "id": 3999141323, "lat": -16.9479762, "lon": -49.4249104}, {"type": "node", "id": 3999141324, "lat": -16.9480097, "lon": -49.4247727}, {"type": "node", "id": 3999141325, "lat": -16.9480196, "lon": -49.4248774}, {"type": "node", "id": 3999141326, "lat": -16.9480647, "lon": -49.4248538}, {"type": "node", "id": 3999141328, "lat": -16.9482044, "lon": -49.4248376}, {"type": "node", "id": 3999141330, "lat": -16.9483873, "lon": -49.4247831}, {"type": "node", "id": 3999141331, "lat": -16.9483921, "lon": -49.4244098}, {"type": "node", "id": 3999141332, "lat": -16.9484485, "lon": -49.4246125}, {"type": "node", "id": 3999141333, "lat": -16.948457, "lon": -49.424367}, {"type": "node", "id": 3999141334, "lat": -16.948457, "lon": -49.4247993}, {"type": "node", "id": 3999141335, "lat": -16.9484627, "lon": -49.4244629}, {"type": "node", "id": 3999141336, "lat": -16.9484923, "lon": -49.4246916}, {"type": "node", "id": 3999141337, "lat": -16.9485403, "lon": -49.4248229}, {"type": "node", "id": 3999141338, "lat": -16.9485417, "lon": -49.4243833}, {"type": "node", "id": 3999141339, "lat": -16.9485657, "lon": -49.4247506}, {"type": "node", "id": 3999141340, "lat": -16.9485981, "lon": -49.4242446}, {"type": "node", "id": 3999141341, "lat": -16.9486419, "lon": -49.4248715}, {"type": "node", "id": 3999141342, "lat": -16.9486489, "lon": -49.4242712}, {"type": "node", "id": 3999141344, "lat": -16.9486969, "lon": -49.4248288}, {"type": "node", "id": 3999141352, "lat": -16.9505156, "lon": -49.4258181}, {"type": "node", "id": 3999141361, "lat": -16.9523645, "lon": -49.4267638}, {"type": "node", "id": 3999141392, "lat": -16.9582337, "lon": -49.4286383}, {"type": "node", "id": 3999141414, "lat": -16.9600225, "lon": -49.4287855}, {"type": "node", "id": 3999141432, "lat": -16.9640642, "lon": -49.4291535}, {"type": "node", "id": 3999141471, "lat": -16.9720957, "lon": -49.429883}, {"type": "node", "id": 3999141493, "lat": -16.9763524, "lon": -49.4302622}, {"type": "node", "id": 3999141494, "lat": -16.977044, "lon": -49.4302401}, {"type": "node", "id": 3999141497, "lat": -16.9772499, "lon": -49.4302153}, {"type": "node", "id": 3999141500, "lat": -16.9776683, "lon": -49.4301366}, {"type": "node", "id": 3999141501, "lat": -16.9779362, "lon": -49.4300718}, {"type": "node", "id": 3999141505, "lat": -16.9786779, "lon": -49.4298427}, {"type": "node", "id": 3999141508, "lat": -16.9791696, "lon": -49.4296786}, {"type": "node", "id": 3999141529, "lat": -16.982273, "lon": -49.4287277}, {"type": "node", "id": 3999141548, "lat": -16.9836059, "lon": -49.428598}, {"type": "node", "id": 3999141553, "lat": -16.9847351, "lon": -49.4287466}, {"type": "node", "id": 3999141565, "lat": -16.9856743, "lon": -49.4290658}, {"type": "node", "id": 3999141568, "lat": -16.9863543, "lon": -49.429449}, {"type": "node", "id": 3999141569, "lat": -16.9865079, "lon": -49.4295575}, {"type": "node", "id": 3999141571, "lat": -16.9874935, "lon": -49.4304525}, {"type": "node", "id": 3999141573, "lat": -16.9878379, "lon": -49.430822}, {"type": "node", "id": 3999141609, "lat": -17.0002781, "lon": -49.4498052}, {"type": "node", "id": 3999141613, "lat": -17.0007464, "lon": -49.4501149}, {"type": "node", "id": 3999141615, "lat": -17.0017057, "lon": -49.4506047}, {"type": "node", "id": 3999141619, "lat": -17.0027806, "lon": -49.4509145}, {"type": "node", "id": 3999141625, "lat": -17.0046201, "lon": -49.4513157}, {"type": "node", "id": 3999141636, "lat": -17.0083695, "lon": -49.4521666}, {"type": "node", "id": 3999141656, "lat": -17.0091522, "lon": -49.4522322}, {"type": "node", "id": 3999141660, "lat": -17.0096348, "lon": -49.4521892}, {"type": "node", "id": 3999141672, "lat": -17.010424, "lon": -49.4520888}, {"type": "node", "id": 3999141685, "lat": -17.0124791, "lon": -49.4515228}, {"type": "node", "id": 3999141699, "lat": -17.0142789, "lon": -49.4510239}, {"type": "node", "id": 3999141734, "lat": -17.0244419, "lon": -49.4481551}, {"type": "node", "id": 3999141735, "lat": -17.025174, "lon": -49.4479569}, {"type": "node", "id": 3999141736, "lat": -17.0258462, "lon": -49.4477065}, {"type": "node", "id": 3999141737, "lat": -17.0262053, "lon": -49.447548}, {"type": "node", "id": 3999141738, "lat": -17.0265803, "lon": -49.4473707}, {"type": "node", "id": 3999141739, "lat": -17.0295582, "lon": -49.4457749}, {"type": "node", "id": 3999141740, "lat": -17.0303004, "lon": -49.4454159}, {"type": "node", "id": 3999141741, "lat": -17.031185, "lon": -49.4451334}, {"type": "node", "id": 3999141743, "lat": -17.0318224, "lon": -49.4449736}, {"type": "node", "id": 3999141751, "lat": -17.0388676, "lon": -49.4432348}, {"type": "node", "id": 3999141753, "lat": -17.039082, "lon": -49.4431404}, {"type": "node", "id": 3999141754, "lat": -17.0394882, "lon": -49.442928}, {"type": "node", "id": 3999141758, "lat": -17.0402527, "lon": -49.4422907}, {"type": "node", "id": 3999141970, "lat": -17.0650285, "lon": -49.4266439}, {"type": "node", "id": 3999141972, "lat": -17.0652774, "lon": -49.42651}, {"type": "node", "id": 3999141986, "lat": -17.0659116, "lon": -49.426169}, {"type": "node", "id": 3999142006, "lat": -17.0674541, "lon": -49.4253369}, {"type": "node", "id": 3999142010, "lat": -17.0702236, "lon": -49.4238588}, {"type": "node", "id": 3999142017, "lat": -17.0736813, "lon": -49.4219381}, {"type": "node", "id": 3999142018, "lat": -17.0743244, "lon": -49.4213982}, {"type": "node", "id": 3999142030, "lat": -17.0812295, "lon": -49.4137458}, {"type": "node", "id": 3999142229, "lat": -17.1117672, "lon": -49.4047068}, {"type": "node", "id": 3999142569, "lat": -17.1267138, "lon": -49.4186673}, {"type": "node", "id": 3999142661, "lat": -17.198649, "lon": -49.424232}, {"type": "node", "id": 3999142709, "lat": -17.2142923, "lon": -49.4213085}, {"type": "node", "id": 3999142714, "lat": -17.2200098, "lon": -49.422034}, {"type": "node", "id": 3999142760, "lat": -17.2357433, "lon": -49.4163123}, {"type": "node", "id": 4088174319, "lat": -17.2301915, "lon": -49.419973}, {"type": "node", "id": 4100161146, "lat": -17.2664, "lon": -49.395993}, {"type": "node", "id": 4393741253, "lat": -16.862926, "lon": -49.256466}, {"type": "node", "id": 4393753853, "lat": -16.8622277, "lon": -49.2565256}, {"type": "node", "id": 4393754618, "lat": -16.8615804, "lon": -49.2565989}, {"type": "node", "id": 4460889788, "lat": -16.9255161, "lon": -49.362489}, {"type": "node", "id": 4460899056, "lat": -16.8650623, "lon": -49.2563552}, {"type": "node", "id": 4460899057, "lat": -16.8650982, "lon": -49.256482}, {"type": "node", "id": 4460899058, "lat": -16.8651605, "lon": -49.2568689}, {"type": "node", "id": 4460899059, "lat": -16.8652169, "lon": -49.2571934}, {"type": "node", "id": 4460899060, "lat": -16.8653195, "lon": -49.2573672}, {"type": "node", "id": 4460918240, "lat": -16.9464439, "lon": -49.3996914}, {"type": "node", "id": 4460918241, "lat": -16.9465871, "lon": -49.4011734}, {"type": "node", "id": 4460918242, "lat": -16.9466709, "lon": -49.4021039}, {"type": "node", "id": 4460918243, "lat": -16.946816, "lon": -49.4039058}, {"type": "node", "id": 4460918244, "lat": -16.9471106, "lon": -49.4062262}, {"type": "node", "id": 4460918245, "lat": -16.9473751, "lon": -49.4081364}, {"type": "node", "id": 4460918246, "lat": -16.9474991, "lon": -49.4089203}, {"type": "node", "id": 4520850384, "lat": -16.8527615, "lon": -49.4138792}, {"type": "node", "id": 4680036193, "lat": -16.8357973, "lon": -49.2467359}, {"type": "node", "id": 4680036194, "lat": -16.835824, "lon": -49.2467356}, {"type": "node", "id": 4680036195, "lat": -16.8358498, "lon": -49.2467726}, {"type": "node", "id": 4680036196, "lat": -16.8358388, "lon": -49.246802}, {"type": "node", "id": 4680036197, "lat": -16.8358161, "lon": -49.2468139}, {"type": "node", "id": 4680036198, "lat": -16.8357912, "lon": -49.2468085}, {"type": "node", "id": 4680036199, "lat": -16.8357736, "lon": -49.2467843}, {"type": "node", "id": 4680036200, "lat": -16.8357771, "lon": -49.2467542}, {"type": "node", "id": 5171626082, "lat": -16.8460514, "lon": -49.4037352}, {"type": "node", "id": 5171646163, "lat": -16.8939485, "lon": -49.4403883}, {"type": "node", "id": 5171646169, "lat": -16.8880194, "lon": -49.4388801}, {"type": "node", "id": 5172776947, "lat": -16.9245479, "lon": -49.4454579}, {"type": "node", "id": 5172776949, "lat": -16.9245728, "lon": -49.445432}, {"type": "node", "id": 5384231433, "lat": -16.8661575, "lon": -49.4370389}, {"type": "node", "id": 5384231441, "lat": -16.8997919, "lon": -49.4422458}, {"type": "node", "id": 6398572567, "lat": -16.919737, "lon": -49.4508511}, {"type": "node", "id": 6398572568, "lat": -16.9214135, "lon": -49.3494259}, {"type": "node", "id": 6398572569, "lat": -16.9202075, "lon": -49.3481424}, {"type": "node", "id": 6398572570, "lat": -16.8887124, "lon": -49.3105779}, {"type": "node", "id": 6565108686, "lat": -16.9556407, "lon": -49.4283472}, {"type": "node", "id": 6565108687, "lat": -16.9495235, "lon": -49.4223223}, {"type": "node", "id": 6565108688, "lat": -16.9495758, "lon": -49.4153894}, {"type": "node", "id": 6565108689, "lat": -16.947617, "lon": -49.409336}, {"type": "node", "id": 6565108690, "lat": -16.9463884, "lon": -49.3995138}, {"type": "node", "id": 6565108691, "lat": -16.9460919, "lon": -49.399178}, {"type": "node", "id": 6565108692, "lat": -16.9436617, "lon": -49.3981901}, {"type": "node", "id": 6565108693, "lat": -16.9431264, "lon": -49.3977488}, {"type": "node", "id": 6565108694, "lat": -16.94141, "lon": -49.3953198}, {"type": "node", "id": 6565108695, "lat": -16.9410185, "lon": -49.3927228}, {"type": "node", "id": 6565108696, "lat": -16.9408891, "lon": -49.3923294}, {"type": "node", "id": 6565108697, "lat": -16.9402938, "lon": -49.3911222}, {"type": "node", "id": 6565108698, "lat": -16.9391495, "lon": -49.3896925}, {"type": "node", "id": 6565108699, "lat": -16.938032, "lon": -49.3884923}, {"type": "node", "id": 6565108700, "lat": -16.9325637, "lon": -49.3777826}, {"type": "node", "id": 6565108701, "lat": -16.9312579, "lon": -49.3760746}, {"type": "node", "id": 6565108702, "lat": -16.9284383, "lon": -49.3739914}, {"type": "node", "id": 6565108703, "lat": -16.925711, "lon": -49.3681903}, {"type": "node", "id": 6565108704, "lat": -16.9264379, "lon": -49.3509279}, {"type": "node", "id": 6565108705, "lat": -16.9259632, "lon": -49.3505698}, {"type": "node", "id": 6565108706, "lat": -16.9249586, "lon": -49.3501917}, {"type": "node", "id": 6565108707, "lat": -16.9210646, "lon": -49.3492314}, {"type": "node", "id": 6565108708, "lat": -16.9204846, "lon": -49.3486789}, {"type": "node", "id": 6565108709, "lat": -16.9189411, "lon": -49.3443605}, {"type": "node", "id": 6565108710, "lat": -16.9186094, "lon": -49.3414731}, {"type": "node", "id": 6565108711, "lat": -16.9185575, "lon": -49.3410172}, {"type": "node", "id": 6565108721, "lat": -16.900871, "lon": -49.3235221}, {"type": "node", "id": 6565108722, "lat": -16.9008833, "lon": -49.3235521}, {"type": "node", "id": 6565108723, "lat": -16.9009045, "lon": -49.323576}, {"type": "node", "id": 6565108724, "lat": -16.9009321, "lon": -49.3235911}, {"type": "node", "id": 6565108725, "lat": -16.900963, "lon": -49.3235957}, {"type": "node", "id": 6565108726, "lat": -16.9010149, "lon": -49.3235769}, {"type": "node", "id": 6565108727, "lat": -16.9010325, "lon": -49.323559}, {"type": "node", "id": 6565108728, "lat": -16.9010449, "lon": -49.323537}, {"type": "node", "id": 6565108729, "lat": -16.9010235, "lon": -49.3234303}, {"type": "node", "id": 6565108730, "lat": -16.9009999, "lon": -49.3234133}, {"type": "node", "id": 6565108731, "lat": -16.9009724, "lon": -49.3234047}, {"type": "node", "id": 6565108732, "lat": -16.9009437, "lon": -49.3234055}, {"type": "node", "id": 6565108733, "lat": -16.9009166, "lon": -49.3234154}, {"type": "node", "id": 6565108734, "lat": -16.9008938, "lon": -49.3234336}, {"type": "node", "id": 6565108735, "lat": -16.8979507, "lon": -49.3218423}, {"type": "node", "id": 6565108737, "lat": -16.9442964, "lon": -49.4305546}, {"type": "node", "id": 6565108738, "lat": -16.9408906, "lon": -49.4341544}, {"type": "node", "id": 6565108787, "lat": -16.9266391, "lon": -49.443608}, {"type": "node", "id": 6565108788, "lat": -16.9275403, "lon": -49.4428799}, {"type": "node", "id": 6565108827, "lat": -16.9032525, "lon": -49.4437609}, {"type": "node", "id": 6565108843, "lat": -16.9232842, "lon": -49.4468893}, {"type": "node", "id": 6565108844, "lat": -16.92394, "lon": -49.4461415}, {"type": "node", "id": 6565108857, "lat": -16.8961709, "lon": -49.4409037}, {"type": "node", "id": 6565108860, "lat": -16.8885707, "lon": -49.4390276}, {"type": "node", "id": 6565108861, "lat": -16.8571305, "lon": -49.4398953}, {"type": "node", "id": 6819732858, "lat": -16.8989568, "lon": -49.4418873}, {"type": "node", "id": 7209255116, "lat": -16.8506344, "lon": -49.4093251, "tags": {"traffic_calming": "hump"}}, {"type": "node", "id": 7209255117, "lat": -16.8505931, "lon": -49.4093699, "tags": {"traffic_calming": "hump"}}, {"type": "node", "id": 8193794578, "lat": -17.0497979, "lon": -49.4349209}, {"type": "node", "id": 8193824489, "lat": -17.0507829, "lon": -49.4343792}, {"type": "node", "id": 8246917818, "lat": -16.8593623, "lon": -49.4255495}, {"type": "node", "id": 8247156627, "lat": -16.8907752, "lon": -49.4395855}, {"type": "node", "id": 8247362818, "lat": -16.8564742, "lon": -49.4647743}, {"type": "node", "id": 8250915912, "lat": -16.8998521, "lon": -49.4422679}, {"type": "node", "id": 8251419260, "lat": -16.9033574, "lon": -49.4438303}, {"type": "node", "id": 8253565477, "lat": -16.9199078, "lon": -49.3472982}, {"type": "node", "id": 8253582138, "lat": -16.9117105, "lon": -49.3305063}, {"type": "node", "id": 8253582139, "lat": -16.9117624, "lon": -49.330449}, {"type": "node", "id": 8253652738, "lat": -16.9319034, "lon": -49.4394341}, {"type": "node", "id": 8253652739, "lat": -16.9306102, "lon": -49.4403112}, {"type": "node", "id": 8253676406, "lat": -16.9409998, "lon": -49.4340758}, {"type": "node", "id": 8253696752, "lat": -16.9288627, "lon": -49.4417757}, {"type": "node", "id": 8253907708, "lat": -16.9253421, "lon": -49.4447005}, {"type": "node", "id": 8253907710, "lat": -16.9262214, "lon": -49.4439455}, {"type": "node", "id": 8253907716, "lat": -16.927079, "lon": -49.4432526}, {"type": "node", "id": 8254317354, "lat": -16.9227673, "lon": -49.3497549}, {"type": "node", "id": 8254616787, "lat": -17.2673133, "lon": -49.3954702}, {"type": "node", "id": 8256296329, "lat": -16.8949657, "lon": -49.3183264}, {"type": "node", "id": 8256296342, "lat": -16.911935, "lon": -49.3305841}, {"type": "node", "id": 8256329954, "lat": -16.8956929, "lon": -49.3192859}, {"type": "node", "id": 8273796125, "lat": -16.9255289, "lon": -49.362413}, {"type": "node", "id": 8277397716, "lat": -17.1175807, "lon": -49.4097315}, {"type": "node", "id": 8277561108, "lat": -17.1548158, "lon": -49.4326221}, {"type": "node", "id": 8277762433, "lat": -17.1033324, "lon": -49.404159}, {"type": "node", "id": 8277762470, "lat": -17.1141899, "lon": -49.4066729}, {"type": "node", "id": 8277762506, "lat": -17.1149192, "lon": -49.4073408}, {"type": "node", "id": 8278104979, "lat": -17.1595188, "lon": -49.431198}, {"type": "node", "id": 8278420899, "lat": -17.1642655, "lon": -49.429835}, {"type": "node", "id": 8299204082, "lat": -17.2170377, "lon": -49.4216457}, {"type": "node", "id": 8314334858, "lat": -17.1987219, "lon": -49.4242008}, {"type": "node", "id": 8314373632, "lat": -17.1912269, "lon": -49.4274089}, {"type": "node", "id": 8314397954, "lat": -17.1925726, "lon": -49.4268315}, {"type": "node", "id": 8314422997, "lat": -17.1883744, "lon": -49.4286329}, {"type": "node", "id": 8314850787, "lat": -17.1934411, "lon": -49.4264594}, {"type": "node", "id": 8341498550, "lat": -16.9497512, "lon": -49.4157609}, {"type": "node", "id": 8341498551, "lat": -16.9497794, "lon": -49.415887}, {"type": "node", "id": 8341605540, "lat": -16.9470554, "lon": -49.4257031}, {"type": "node", "id": 8353774275, "lat": -16.8448131, "lon": -49.2522}, {"type": "node", "id": 8367407125, "lat": -16.8402665, "lon": -49.396551}, {"type": "node", "id": 8367407131, "lat": -16.8417409, "lon": -49.3983956}, {"type": "node", "id": 8428809790, "lat": -16.8650976, "lon": -49.2562446}, {"type": "node", "id": 8428809791, "lat": -16.8651823, "lon": -49.2563324}, {"type": "node", "id": 8428809792, "lat": -16.8652349, "lon": -49.2564887}, {"type": "node", "id": 8428809793, "lat": -16.8652574, "lon": -49.2566697}, {"type": "node", "id": 8428809794, "lat": -16.8652105, "lon": -49.2563901}, {"type": "node", "id": 8428809795, "lat": -16.8650251, "lon": -49.2563096}, {"type": "node", "id": 8428809796, "lat": -16.8650841, "lon": -49.2564156}, {"type": "node", "id": 8428809797, "lat": -16.8649384, "lon": -49.2562573}, {"type": "node", "id": 8428809798, "lat": -16.8649927, "lon": -49.2562862}, {"type": "node", "id": 8428809799, "lat": -16.8651412, "lon": -49.2562761}, {"type": "node", "id": 8428809800, "lat": -16.8650101, "lon": -49.2562241}, {"type": "node", "id": 8434859585, "lat": -16.8657114, "lon": -49.2603219}, {"type": "node", "id": 8436883191, "lat": -16.8718506, "lon": -49.2867366}, {"type": "node", "id": 8437034817, "lat": -16.870169, "lon": -49.2828575}, {"type": "node", "id": 8437034819, "lat": -16.8702492, "lon": -49.2830228}, {"type": "node", "id": 8437034827, "lat": -16.8710269, "lon": -49.2847042}, {"type": "node", "id": 8437034828, "lat": -16.871118, "lon": -49.2849147}, {"type": "node", "id": 8437034829, "lat": -16.8704994, "lon": -49.2835502}, {"type": "node", "id": 8437034830, "lat": -16.8708203, "lon": -49.2842616}, {"type": "node", "id": 8437034831, "lat": -16.871419, "lon": -49.2856155}, {"type": "node", "id": 8437034832, "lat": -16.8717085, "lon": -49.2863096}, {"type": "node", "id": 8440346401, "lat": -16.8536199, "lon": -49.4195804}, {"type": "node", "id": 8440375441, "lat": -16.8567126, "lon": -49.4232098}, {"type": "node", "id": 8440375453, "lat": -16.855327, "lon": -49.4219857}, {"type": "node", "id": 8444420243, "lat": -16.8439815, "lon": -49.4011572}, {"type": "node", "id": 8444852980, "lat": -16.8513824, "lon": -49.4102785}, {"type": "node", "id": 8444852981, "lat": -16.8468464, "lon": -49.4047076}, {"type": "node", "id": 8447875673, "lat": -16.888805, "lon": -49.3107054}, {"type": "node", "id": 8447875702, "lat": -16.8856916, "lon": -49.306942}, {"type": "node", "id": 8452012363, "lat": -16.8858237, "lon": -49.3070983}, {"type": "node", "id": 8452012364, "lat": -16.8857256, "lon": -49.3070818}, {"type": "node", "id": 8452012365, "lat": -16.8855273, "lon": -49.3068928}, {"type": "node", "id": 8452012366, "lat": -16.8855029, "lon": -49.3067038}, {"type": "node", "id": 8452012367, "lat": -16.8854465, "lon": -49.3065374}, {"type": "node", "id": 8452012368, "lat": -16.8856242, "lon": -49.3067519}, {"type": "node", "id": 8452012369, "lat": -16.8853089, "lon": -49.3064678}, {"type": "node", "id": 8452012370, "lat": -16.8854112, "lon": -49.3065139}, {"type": "node", "id": 8452012371, "lat": -16.8855151, "lon": -49.3066138}, {"type": "node", "id": 8452012372, "lat": -16.8856588, "lon": -49.3068197}, {"type": "node", "id": 8452012373, "lat": -16.8857878, "lon": -49.3069679}, {"type": "node", "id": 8452012374, "lat": -16.8858359, "lon": -49.3070014}, {"type": "node", "id": 8452012375, "lat": -16.8858918, "lon": -49.3070704}, {"type": "node", "id": 8452012376, "lat": -16.8859533, "lon": -49.3072544}, {"type": "node", "id": 8452012380, "lat": -16.8855254, "lon": -49.3070101}, {"type": "node", "id": 8452012381, "lat": -16.8856248, "lon": -49.3070725}, {"type": "node", "id": 8452012383, "lat": -16.8856691, "lon": -49.3069112}, {"type": "node", "id": 8550767073, "lat": -16.8357854, "lon": -49.2467441}, {"type": "node", "id": 8550767074, "lat": -16.8357363, "lon": -49.246708}, {"type": "node", "id": 8550767075, "lat": -16.8358372, "lon": -49.2467439}, {"type": "node", "id": 8550767076, "lat": -16.8358106, "lon": -49.2467332}, {"type": "node", "id": 8550767077, "lat": -16.8357856, "lon": -49.2467432}, {"type": "node", "id": 8550767078, "lat": -16.8358471, "lon": -49.2467885}, {"type": "node", "id": 8550767079, "lat": -16.8358284, "lon": -49.2468099}, {"type": "node", "id": 8550767080, "lat": -16.8358032, "lon": -49.2468134}, {"type": "node", "id": 8550767081, "lat": -16.8357802, "lon": -49.2467982}, {"type": "node", "id": 8550767082, "lat": -16.8357726, "lon": -49.2467689}, {"type": "node", "id": 8550767083, "lat": -16.8358463, "lon": -49.2467569}, {"type": "node", "id": 8550767084, "lat": -16.8358801, "lon": -49.2468515}, {"type": "node", "id": 8550790775, "lat": -16.8324098, "lon": -49.2457062}, {"type": "node", "id": 8787427309, "lat": -16.8650846, "lon": -49.4306024}, {"type": "node", "id": 8986834814, "lat": -16.8574508, "lon": -49.2566067}, {"type": "node", "id": 8986834815, "lat": -16.8577794, "lon": -49.2566845}, {"type": "node", "id": 8986834816, "lat": -16.8584057, "lon": -49.2567703}, {"type": "node", "id": 8998538465, "lat": -16.8727695, "lon": -49.2894688}, {"type": "node", "id": 8998605253, "lat": -16.8409217, "lon": -49.3973711}, {"type": "node", "id": 8998605257, "lat": -16.8391197, "lon": -49.395124}, {"type": "node", "id": 8998605261, "lat": -16.8394299, "lon": -49.395515}, {"type": "node", "id": 9000216106, "lat": -16.8436184, "lon": -49.4007089}, {"type": "node", "id": 9000427821, "lat": -16.8665159, "lon": -49.2656915}, {"type": "node", "id": 9000462302, "lat": -16.8562107, "lon": -49.2561386}, {"type": "node", "id": 9000462309, "lat": -16.8561156, "lon": -49.2561013}, {"type": "node", "id": 9001170162, "lat": -16.8636126, "lon": -49.2563983}, {"type": "node", "id": 9001871531, "lat": -16.8352648, "lon": -49.2446667}, {"type": "way", "id": 30768231, "nodes": [340260024, 8550790775, 340260181, 340260126, 3135860552, 340260155], "tags": {"highway": "primary", "lanes": "2", "name": "Avenida Teodomiro de Souza", "oneway": "yes"}}, {"type": "way", "id": 30776262, "nodes": [340337859, 340337891, 340337892, 340337893, 340337894, 340337895, 340337896, 340337897, 340337898], "tags": {"highway": "primary", "incorrect:junction": "roundabout", "junction": "circular", "oneway": "yes", "surface": "paved"}}, {"type": "way", "id": 30776263, "nodes": [340337888, 340337908, 340337909, 340337911], "tags": {"highway": "primary_link", "oneway": "yes", "surface": "paved"}}, {"type": "way", "id": 30776279, "nodes": [340337911, 2986286013, 340337968, 340337891], "tags": {"highway": "primary_link", "oneway": "yes", "surface": "paved"}}, {"type": "way", "id": 30776282, "nodes": [340337716, 340337976, 340337894], "tags": {"highway": "primary", "oneway": "yes", "ref": "GO-219", "source": "IBGE", "surface": "paved"}}, {"type": "way", "id": 30776285, "nodes": [340337974, 3999141153, 340337980, 340337981, 340337885], "tags": {"highway": "primary_link", "oneway": "yes", "surface": "paved"}}, {"type": "way", "id": 164957245, "nodes": [3999141132, 3999141130, 8444852981, 5171626082, 2868392941, 8444420243, 9000216106, 2868392916, 8367407131, 2868392894, 8998605253, 2868392880, 8367407125, 2868392877, 2868392872, 2868392868, 8998605261, 8998605257, 2868392860, 2868392857, 2868392853, 2868392850, 3135514077], "tags": {"IBGE:CD_ADMINIS": "estadual", "highway": "primary", "note": "Removed name = GO 040", "ref": "GO-040"}}, {"type": "way", "id": 164957246, "nodes": [340337895, 340337973, 340337974], "tags": {"highway": "primary_link", "oneway": "yes", "surface": "paved"}}, {"type": "way", "id": 164957247, "nodes": [340337892, 340337955, 340337956, 340337716], "tags": {"highway": "primary", "oneway": "yes", "ref": "GO-219", "source": "IBGE", "surface": "paved"}}, {"type": "way", "id": 294680133, "nodes": [2982733648, 1771628573, 589546430, 2986421979, 2986421982, 2986421980, 2986421981, 589546428, 1448720889, 1448721195, 1448721109, 589546426, 8254616787, 3146847935, 4100161146, 2986421978, 1448721006, 2986421977, 2986421976, 1448721133, 2986421975, 2986421974, 2986421972, 2986421973, 2986421971, 2986421970, 3999142760, 2986421969, 4088174319, 589546425, 2986421965, 2986421967, 2986421966, 2986421968, 589546424, 2986421963, 2986421964, 2986421962, 2986421961, 3999142714, 2986421960, 8299204082, 2986421959, 3999142709, 589546423, 2986421958, 2986421957, 2986421956, 2986421955, 8314334858, 3999142661, 2986421954, 8314850787, 8314397954, 8314373632, 8314422997, 589546421, 2986421953, 2986421949, 2986421952, 2986421950, 2986421951, 589546408, 2986421948, 2986421947, 2986421946, 2986421941, 2986421943, 2986421942, 2986421944, 589546406, 8278420899, 2986421945, 2986421940, 2986421939, 8278104979, 2986421938, 8277561108, 2986421937, 2986421936, 2986421935, 2986421934, 589546403, 2986421933, 2986421831, 2986421832, 589546399, 2986421830, 589546396, 2986421829, 2986421828, 2986421825, 2986421827, 2986421826, 2986421824, 3999142569, 589546393, 2986421823, 2986421821, 2986421822, 2986421819, 2986434868, 2986430565, 8277397716, 2986430212, 2986427991, 2986421820, 2986427970, 2986429325, 8277762506, 2986423031, 8277762470, 589546390, 2986421818, 3999142229, 589546386, 2986421817, 2986421816, 589546383, 2986421815, 2986421813, 2986421814, 8277762433, 2986421811, 2986421812, 2986421810, 2986421809, 2986421806, 2986421808, 2986421807, 2986421802, 2986421803, 2986421804, 2986421805, 589546379, 2986421800, 2986421801, 2986421799, 2986421798, 2986421796, 3999142030, 2986421797, 2986421795, 589546378, 3999142018, 2986421794, 3999142017, 2986421793, 2986421792, 3999142010, 2986421791, 3999142006, 2986421790, 3999141986, 3999141972, 3999141970, 2986421789, 2986421788, 2986421787, 2986421786, 589546377, 2986421785, 8193824489, 2986421784, 8193794578, 2986421781, 2986421782, 2986421783, 2986421780, 2986421779, 589546376, 2986421778, 2986421775, 3999141758, 2986421776, 3999141754, 2986421777, 3999141753, 3999141751, 589546375, 589546372, 2986421774, 2986421770, 3999141743, 3999141741, 2986421771, 2986421773, 3999141740, 2986421772, 3999141739, 2986421766, 2986421767, 2986421769, 2986421768, 2986421763, 3999141738, 3999141737, 3999141736, 2986421764, 3999141735, 2986421765, 3999141734, 589546369, 589546365, 3999141699, 589546362, 3999141685, 2986421759, 3999141672, 2986421760, 3999141660, 2986421761, 3999141656, 589546360, 3999141636, 2986421758, 2986421757, 2986421756, 3999141625, 589546357, 3999141619, 2986421755, 3999141615, 2986421754, 3999141613, 3999141609, 589546355, 2986421753, 2986421750, 2986421752, 2986421751, 2986421749, 589546351, 2986421748, 589546348, 2986421747, 589546346, 2986421746, 2986421745, 589546342, 3999141573, 2986421743, 3999141571, 2986421744, 589546340, 3999141569, 3999141568, 2986421742, 3999141565, 2986421741, 3999141553, 589546337, 3999141548, 2986421739, 2986421740, 3999141529, 589546332, 2986421738, 589546330, 3999141508, 3999141505, 2986421737, 3999141501, 3999141500, 3999141497, 3999141494, 589546326, 3999141493, 2986421736, 2986421735, 589546323, 3999141471, 3999141432, 589546320, 2986421734, 3999141414, 589546317, 3999141392, 2986421732, 2986421733, 6565108686, 589546315, 2986421731, 2986421730, 3999141361, 589546314, 3999141352, 2986421727, 2986421728, 2986421729, 589546313], "tags": {"IBGE:CD_ADMINIS": "estadual", "highway": "primary", "ref": "GO-040"}}, {"type": "way", "id": 294986618, "nodes": [340337859, 2986286716, 2986286717, 340337898], "tags": {"IBGE:CD_ADMINIS": "estadual", "highway": "primary", "ref": "GO-040", "surface": "paved"}}, {"type": "way", "id": 294990287, "nodes": [2986316281, 3999141340, 3999141333, 3999141331, 2986314088], "tags": {"highway": "primary", "name": "GO-319", "oneway": "yes", "ref": "GO-319"}}, {"type": "way", "id": 294990294, "nodes": [2986314852, 3999141321, 3999141323, 3999141325, 3999141326, 2986314082], "tags": {"IBGE:CD_ADMINIS": "estadual", "highway": "primary", "oneway": "yes", "ref": "GO-040", "surface": "paved"}}, {"type": "way", "id": 294990802, "nodes": [2986314080, 3999141324, 3999141322, 3999141320, 2986314852], "tags": {"IBGE:CD_ADMINIS": "estadual", "highway": "primary", "oneway": "yes", "ref": "GO-040", "surface": "paved"}}, {"type": "way", "id": 294990811, "nodes": [2986314852, 589546301, 8341605540, 2986313284, 589546299, 2986313283, 589546296, 6565108737, 2986313282, 589546294, 2986313281, 8253676406, 6565108738, 589546291, 2986313280, 2986313279, 2986313277, 3999141313, 8253652738, 2986313278, 8253652739, 589546287, 8253696752, 2986313276, 6565108788, 8253907716, 6565108787, 8253907710, 260403412, 8253907708, 260403410, 5172776949, 5172776947, 6565108844, 6565108843, 260403408, 3135649104, 260403407, 765258760, 3135649092, 6398572567, 765258748, 765258782, 765271327, 3163960964, 765271480, 765271349, 260403405], "tags": {"IBGE:CD_ADMINIS": "estadual", "highway": "primary", "ref": "GO-040", "surface": "paved"}}, {"type": "way", "id": 294990830, "nodes": [3999141330, 3999141334, 3999141337, 3999141341, 589546313], "tags": {"IBGE:CD_ADMINIS": "estadual", "highway": "primary", "oneway": "yes", "ref": "GO-040"}}, {"type": "way", "id": 294990844, "nodes": [589546313, 3999141344, 3999141339, 3999141336, 3999141332], "tags": {"IBGE:CD_ADMINIS": "estadual", "highway": "primary", "oneway": "yes", "ref": "GO-040", "surface": "paved"}}, {"type": "way", "id": 294990849, "nodes": [2986316281, 2986316280, 2986316279, 2986316278, 6565108687, 589546672, 589546673, 589546676, 8341498551, 8341498550, 6565108688, 589546678, 589546681, 6565108689, 4460918246, 4460918245, 589546683, 4460918244, 4460918243, 589546685, 4460918242, 4460918241, 4460918240, 6565108690, 589546688, 6565108691, 589546690, 2505930182, 6565108692, 2505930183, 6565108693, 589546694, 2505930184, 2505937998, 589546698, 6565108694, 2505930185, 589546699, 6565108695, 6565108696, 589546702, 6565108697, 589546704, 6565108698, 2505930186, 6565108699, 589546706, 589546709, 3183405341, 589546711, 3183405154, 3183404877, 3183404911, 589546713, 6565108700, 3183405144, 589546715, 6565108701, 589546717, 3183405158, 589546724, 6565108702, 3183405516, 589546726, 3183405337, 589546729, 589546732, 6565108703, 589546735, 3183405113], "tags": {"highway": "primary", "ref": "GO-319"}}, {"type": "way", "id": 294990923, "nodes": [2986314079, 3999141335, 3999141338, 3999141342, 2986316281], "tags": {"highway": "primary", "oneway": "yes", "ref": "GO-319"}}, {"type": "way", "id": 308270079, "nodes": [8452012366, 8452012369, 340258931, 340259300, 340259301, 340259302, 340259303, 340259304, 340259305, 8998538465, 2024048994, 2024048918, 8436883191, 340259306, 8437034832, 8437034831, 340259307, 8437034828, 8437034827, 8437034830, 8437034829, 8437034819, 8437034817, 2024048927, 2024048965, 3135899489, 2024049084, 340259308, 2024048914, 340259309, 3135860792, 2024048920, 2024048901, 3135860787, 1306312585, 2024049037, 2024049030, 9000427821, 2024049092, 340259311, 2024049107, 2024049117, 2024049023, 8434859585, 3135860782, 2024048910, 2024049007, 2024049113, 4460899060], "tags": {"highway": "primary", "name": "Avenida Espig\u00e3o", "ref": "GO-319", "surface": "paved"}}, {"type": "way", "id": 308270105, "nodes": [3135648624, 3135648835, 3135648850, 3135648858, 3135648875, 3135648885, 3135648890, 3135648896, 3135648901, 3135648909, 8253582138, 3135648919, 3135648921], "tags": {"highway": "primary", "oneway": "yes", "ref": "GO-319", "surface": "paved"}}, {"type": "way", "id": 308270174, "nodes": [6565108729, 6565108730, 6565108731, 6565108732, 6565108733, 6565108734, 3135648621, 3135648622, 6565108721, 6565108722, 6565108723, 6565108724, 6565108725, 3135648624, 6565108726, 6565108727, 6565108728, 3135648628, 3135648625, 3135648623, 6565108729], "tags": {"highway": "primary", "junction": "roundabout", "ref": "GO-319", "surface": "paved"}}, {"type": "way", "id": 308291145, "nodes": [3135860568, 9001871531, 3868769548, 340260155], "tags": {"highway": "primary", "name": "Rua A Poema"}}, {"type": "way", "id": 308291192, "nodes": [340259926, 340259927, 3916712956, 3916746914, 1306302190, 340259928, 8550767084, 4680036196], "tags": {"highway": "primary", "lanes": "2", "name": "Avenida Doutor Ant\u00f4nio Lisboa", "postal_code": "74975-290", "ref": "GO-319", "surface": "paved"}}, {"type": "way", "id": 312484695, "nodes": [3183405113, 589546737], "tags": {"bridge": "yes", "highway": "primary", "layer": "1", "ref": "GO-319"}}, {"type": "way", "id": 312484701, "nodes": [589546737, 3183405349, 3183404934, 3183405279, 4460889788, 8273796125, 589546740, 589546743, 589546744, 589546748, 3135649383, 3135649378, 3135649373, 3135649368, 6565108704, 6565108705, 589546752, 6565108706, 8254317354, 589546759, 6398572568, 6565108707, 589546762, 6565108708, 6398572569, 8253565477, 589546764, 6565108709, 340258290, 6565108710, 6565108711, 340258291, 340258292, 340258293, 340258294, 340258902, 340258904, 340258906, 3135648921], "tags": {"highway": "primary", "ref": "GO-319"}}, {"type": "way", "id": 382244221, "nodes": [8353774275, 3135860762, 340259925, 340259926], "tags": {"highway": "primary", "name": "Rua Jonas Naves", "postal_code": "74975-310", "ref": "GO-319", "surface": "paved"}}, {"type": "way", "id": 382244223, "nodes": [8550767073, 8550767074, 340259929, 340259930], "tags": {"highway": "primary", "lanes": "2", "name": "Rua Caraj\u00e1s", "postal_code": "74975-135", "ref": "GO-319", "surface": "paved"}}, {"type": "way", "id": 383599305, "nodes": [3135860593, 3126429950, 3854338362, 4680036194], "tags": {"alt_name": "Rua T Um", "highway": "primary", "lanes": "2", "name": "Rua T 1", "postal_code": "74975-138", "surface": "asphalt"}}, {"type": "way", "id": 396406431, "nodes": [2986314088, 2986314089, 2986314090, 2986314072, 2986314073, 2986314074, 2986314075, 2986314080], "tags": {"IBGE:CD_ADMINIS": "estadual", "highway": "primary", "name": "Trevo Parag\u00f4nia", "oneway": "yes", "ref": "GO-040", "surface": "paved"}}, {"type": "way", "id": 397092058, "nodes": [765271340, 260403394, 8251419260, 6565108827, 260403390, 3135648620, 8250915912, 5384231441, 3135648615, 6819732858, 3135648589, 3135648576, 260403387, 6565108857, 5171646163, 8247156627, 6565108860, 260403385, 5171646169, 3999141154, 260403383, 260403381, 340337974], "tags": {"IBGE:CD_ADMINIS": "estadual", "highway": "primary", "ref": "GO-040", "surface": "paved"}}, {"type": "way", "id": 397092059, "nodes": [3999141132, 7209255117, 3999141133, 3999141134, 3999141136, 3999141138, 3999141141, 260403334], "tags": {"IBGE:CD_ADMINIS": "estadual", "highway": "primary", "oneway": "yes", "ref": "GO-040"}}, {"type": "way", "id": 397092061, "nodes": [340337911, 260403365, 1765483637, 3999141152, 2505938105, 1765483636, 260403363, 8787427309, 8246917818, 8440375441, 260403362, 8440375453, 3999141151, 260403359, 260403357, 3999141150, 3999141149, 3999141148, 3999141147, 260403355, 8440346401, 260403353, 3999141146, 3999141145, 260403351, 4520850384, 260403349, 3999141144, 260403347, 3999141143, 260403345, 260403344, 3999141142, 260403340, 8444852980, 260403334], "tags": {"IBGE:CD_ADMINIS": "estadual", "highway": "primary", "ref": "GO-040"}}, {"type": "way", "id": 397092067, "nodes": [2986314080, 2986314081, 2986314082], "tags": {"IBGE:CD_ADMINIS": "estadual", "highway": "primary", "name": "Trevo Parag\u00f4nia", "oneway": "yes", "ref": "GO-040", "surface": "paved"}}, {"type": "way", "id": 397092068, "nodes": [3999141330, 2986314077, 2986314078, 3999141332], "tags": {"IBGE:CD_ADMINIS": "estadual", "highway": "primary", "name": "Trevo Parag\u00f4nia", "oneway": "yes", "ref": "GO-040", "surface": "paved"}}, {"type": "way", "id": 397092069, "nodes": [3999141332, 2986314079, 2986314087, 2986314088], "tags": {"IBGE:CD_ADMINIS": "estadual", "highway": "primary", "name": "Trevo Parag\u00f4nia", "oneway": "yes", "ref": "GO-040", "surface": "paved"}}, {"type": "way", "id": 397092070, "nodes": [2986314082, 3999141328, 2986314085, 2986314076, 3999141330], "tags": {"IBGE:CD_ADMINIS": "estadual", "highway": "primary", "name": "Trevo Parag\u00f4nia", "oneway": "yes", "ref": "GO-040", "surface": "paved"}}, {"type": "way", "id": 448154319, "nodes": [4393754618, 340259316, 8986834816, 340259317, 8986834815, 8986834814, 340259318, 340259319, 9000462302, 9000462309, 340259320, 340259345, 340259346, 340259349, 340259922, 340259923, 8353774275], "tags": {"highway": "primary", "ref": "GO-319", "surface": "paved"}}, {"type": "way", "id": 448154320, "nodes": [8428809797, 2024048913, 9001170162, 4393741253, 4393753853, 4393754618], "tags": {"highway": "primary", "name": "Rua L 8", "ref": "GO-319", "surface": "paved"}}, {"type": "way", "id": 449123371, "nodes": [8428809798, 8428809795, 4460899056, 8428809796, 4460899057, 4460899058, 4460899059, 4460899060], "tags": {"highway": "primary", "oneway": "yes", "ref": "GO-319"}}, {"type": "way", "id": 473975132, "nodes": [4680036200, 8550767082, 4680036199, 8550767081, 4680036198, 8550767080, 4680036197, 8550767079, 4680036196, 8550767078, 4680036195, 8550767083, 8550767075, 4680036194, 8550767076, 4680036193, 8550767077, 8550767073, 4680036200], "tags": {"highway": "primary", "junction": "roundabout", "lanes": "1", "oneway": "yes", "ref": "GO-319"}}, {"type": "way", "id": 573386235, "nodes": [4460899060, 2024049118, 8428809793, 8428809792, 8428809794, 8428809791, 8428809799, 8428809790, 8428809800], "tags": {"highway": "primary", "name": "Avenida Espig\u00e3o", "oneway": "yes", "ref": "GO-319", "surface": "paved"}}, {"type": "way", "id": 866723565, "nodes": [340337898, 340337884, 340337885, 340337886, 340337887, 340337888, 340337890, 340337859], "tags": {"highway": "primary", "incorrect:junction": "roundabout", "junction": "circular", "oneway": "yes", "surface": "paved"}}, {"type": "way", "id": 866723566, "nodes": [340337898, 340337974], "tags": {"IBGE:CD_ADMINIS": "estadual", "highway": "primary", "ref": "GO-040", "surface": "paved"}}, {"type": "way", "id": 866723567, "nodes": [340337911, 340337859], "tags": {"IBGE:CD_ADMINIS": "estadual", "highway": "primary", "ref": "GO-040", "surface": "paved"}}, {"type": "way", "id": 886897456, "nodes": [260403334, 3999141140, 3999141139, 3999141137, 3999141135, 7209255116, 3999141132], "tags": {"IBGE:CD_ADMINIS": "estadual", "highway": "primary", "oneway": "yes", "ref": "GO-040"}}, {"type": "way", "id": 886935229, "nodes": [8247362818, 340337691, 340337692, 340337693, 340337694, 340337695, 340337696, 340337697, 340337698, 340337699, 340337700, 340337701, 340337702, 6565108861, 340337703, 340337704, 340337705, 340337706, 340337707, 340337708, 340337709, 340337710, 340337711, 340337712, 2986300443, 340337713, 2986300442, 5384231433, 340337714, 2986300441, 340337715, 340337716], "tags": {"highway": "primary", "oneway": "no", "ref": "GO-219", "surface": "paved"}}, {"type": "way", "id": 887788504, "nodes": [3135648921, 3135648920, 8256296342, 8253582139, 3135648910, 3135648902, 3135648897, 3135648891, 3135648886, 3135648877, 3135648860, 3135648852, 3135648837, 3135648628], "tags": {"highway": "primary", "oneway": "yes", "ref": "GO-319", "surface": "paved"}}, {"type": "way", "id": 907725655, "nodes": [8428809797, 8428809798], "tags": {"highway": "primary", "name": "Rua L 8", "oneway": "yes", "ref": "GO-319", "surface": "paved"}}, {"type": "way", "id": 907725656, "nodes": [8428809800, 8428809797], "tags": {"highway": "primary", "name": "Rua L 8", "oneway": "yes", "ref": "GO-319", "surface": "paved"}}, {"type": "way", "id": 910342325, "nodes": [8452012363, 8447875702], "tags": {"highway": "primary", "name": "Avenida Espig\u00e3o", "ref": "GO-319", "surface": "paved"}}, {"type": "way", "id": 910342326, "nodes": [8447875702, 8452012383, 8452012366], "tags": {"highway": "primary", "name": "Avenida Espig\u00e3o", "ref": "GO-319", "surface": "paved"}}, {"type": "way", "id": 910342327, "nodes": [3135648621, 340258918, 6565108735, 340258920, 340258921, 340258923, 8256329954, 8256296329, 340258924, 340258926, 340258928, 8447875673, 6398572570, 8452012376, 8452012363], "tags": {"highway": "primary", "name": "Avenida Espig\u00e3o", "ref": "GO-319", "surface": "paved"}}, {"type": "way", "id": 910342328, "nodes": [8452012381, 8452012364, 8452012363], "tags": {"highway": "primary_link", "oneway": "yes"}}, {"type": "way", "id": 910342329, "nodes": [8452012366, 8452012365, 8452012380], "tags": {"highway": "primary_link", "oneway": "yes"}}, {"type": "way", "id": 910342330, "nodes": [8447875702, 8452012372, 8452012368, 8452012371, 8452012367, 8452012370, 8452012369], "tags": {"highway": "primary_link", "oneway": "yes"}}, {"type": "way", "id": 910342331, "nodes": [8452012376, 8452012375, 8452012374, 8452012373, 8447875702], "tags": {"highway": "primary_link", "oneway": "yes"}}, {"type": "way", "id": 923733712, "nodes": [3135860593, 3126429954, 3135860568], "tags": {"highway": "primary", "name": "Rua Portiguares"}}]}